Workbook

Sheet 00_Cover
A1: FINANCIAL FEASIBILITY & INVESTMENT DECISION MODEL
A2: FIN 545 · Workshop on Financial Modelling · Lovely Professional University
A4: Venture | B4: Campus Brew Café - a 30-seat café near LPU, Phagwara (GT Road)
A5: Investment question | B5: Does the café create enough value to justify the capital committed? Invest / Invest with Conditions / Do Not Invest
A6: Programme / Section | B6: M.Com
A7: Faculty | B7: Dr Basit
A8: Members / IDs | B8: Harleen
A9: Submission date | B9: 1 October 2026
A10: Model horizon | B10: Year 0 + Year 1 to Year 5 (₹, rupees)
A11: GITHUB link for REPORT | B11: https://github.com/harleenkaur20243/Financial-Modelling.git
A12: LINKED IN URL | B12: www.linkedin.com/in/harleen-kaur-b376a0379
A14: SHEET GUIDE
A15: 01-03 | B15: Project definition · Data & source register · AI research log
A16: 04 | B16: Assumption register (all inputs live here)
A17: 05-11 | B17: Operating drivers · investment & funding · revenue · costs · depreciation · debt · working capital
A18: 12-14 | B18: Income statement · cash flow · balance sheet (integrated; balance check = 0)
A19: 15-16 | B19: Project free cash flow · NPV, IRR, payback and decision
A20: 17-19 | B20: Break-even · scenarios · sensitivity
A21: 20-22 | B21: Dashboard · report & pitch outline · QA checks & viva preparation

Sheet 01_Project_Definition
A1: 01 · Project Definition
A4: Field | B4: Entry | C4: Quality test
A5: Project name | B5: Campus Brew Café | C5: Reader knows what is evaluated
A6: Business problem | B6: Students and staff around LPU want an affordable, comfortable place to eat, meet and study, but seating near the campus gate is limited at peak times. | C6: Measurable: crowding at peak hours
A7: Solution | B7: A 30-seat café serving beverages, snacks and meal combos at student-friendly prices. | C7: Directly linked to the need
A8: Target customer | B8: LPU students, faculty and staff, plus highway travellers on GT Road (LPU has 30,000+ students). | C8: Specific segment
A9: Geography | B9: Near LPU, Chaheru, Phagwara, Punjab (GT Road, NH-44 corridor). | C9: Matches data collected
A10: Business model (one sentence) | B10: The project invests about ₹ the amount in 06_Investment_Funding to provide food and beverages to students and staff in the LPU catchment in Phagwara, generating revenue through per-customer bills. | C10: Revenue mechanism explicit
A11: Unit of economics | B11: One paid customer visit (bill). Customers = seats × seat turns per day × days open. | C11: Measurable revenue unit
A12: Investment objective | B12: Capital for fit-out, equipment, licences, security deposit and opening cash buffer (Year-0 investment). | C12: Linked to 06_Investment_Funding
A13: Investment decision | B13: Invest / Invest with Conditions / Do Not Invest (see 16_Appraisal and 20_Dashboard). | C13: One of three outcomes

Sheet 02_Data_Sources
A1: 02 · Data & Source Register (audit trail)
A2: Official data sources providing reliable, justifiable and useful information
A4: Source ID | B4: Source name | C4: Type | D4: Date | E4: URL / reference | F4: Variable supported | G4: Value / range observed | H4: Unit | I4: Used in model | J4: Verification status / note | K4: Optional action to firm up
A5: SRC-01 | B5: Punjab minimum wages (WageIndicator, from state notification) | C5: Government notification via aggregator | D5: Eff. 1 May 2026 | E5: https://wageindicator.org/en-in/ai/work-in-india/minimum-wage/20772-punjab/ | F5: Staff pay floor | G5: Unskilled ₹518.69/day; semi-skilled ₹553.19; skilled ₹592.84 | H5: ₹/day | I5: 04 Assumptions C | J5: VERIFIED. Aggregator of the official Punjab notification. Salaries in the model are set at or above these floors. | K5: Cross-check with Punjab Labour Dept notification.
A6: SRC-02 | B6: The Tribune: PSERC tariff order FY2025-26 | C6: News report on official order | D6: FY2025-26 | E6: https://www.tribuneindia.com/news/punjab/no-change-in-power-tariff-for-domestic-commercial-users | F6: Electricity tariff | G6: Commercial ₹6.89-7.75 per kWh | H6: ₹/kWh | I6: 04 Assumptions D | J6: VERIFIED. Reputable newspaper reporting the official order. | K6: Check the PSERC FY2026-27 order on pserc.gov.in.
A7: SRC-03 | B7: PSERC Tariff Order FY2026-27 (news summaries: Babushahi, The Fact News) | C7: News report on official order | D7: 6 Mar 2026 | E7: https://www.babushahi.com/full-news.php?id=218071 | F7: Electricity tariff direction | G7: Non-residential energy charges reduced for FY2026-27 | H7: - | I7: 04 Assumptions D | J7: VERIFIED (direction). Confirms ₹7.2/kWh is conservative. | K7: Read the order on pserc.gov.in for the exact commercial rate.
A8: SRC-04 | B8: RBI repo rate (Aug 2026 MPC) | C8: Central bank | D8: Aug 2026 | E8: https://www.5paisa.com/blog/rbi-mpc-meeting-schedule; https://rbi.org.in/ | F8: Base lending rate | G8: Repo rate 5.25% | H8: % | I8: 04 Assumptions I | J8: VERIFIED. Repo rate unchanged at 5.25%. Loan rate = repo + estimated spread. | K8: Ask SBI/PNB for the MSME term-loan rate.
A9: SRC-05 | B9: Trading Economics: India 10-year G-Sec yield | C9: Market data | D9: 15 Sep 2026 | E9: https://tradingeconomics.com/india/government-bond-yield/news/583773 | F9: Risk-free rate | G9: About 7.1% | H9: % | I9: 04 Assumptions K | J9: VERIFIED. Market data provider; RBI/CCIL is the primary source. | K9: Confirm on rbi.org.in / CCIL.
A10: SRC-06 | B10: Trading Economics (CPI Aug 2026) and Akashvani/RBI policy statement | C10: Market data + official | D10: Aug-Sep 2026 | E10: https://newsonair.gov.in/rbi-to-announce-its-first-bi-monthly-monetary-policy-statement-for-financial-year-2026-27-today/ | F10: Inflation / price & cost growth | G10: CPI 4.82% (Aug 2026); RBI FY27 projection 4.6% | H10: % | I10: 04 Assumptions A, C, D | J10: VERIFIED (inflation figures). Pass-through to menu prices is an estimate. | K10: None needed.
A11: SRC-07 | B11: Careers360 (LPU profile) | C11: Education portal | D11: 2022-2024 | E11: https://www.careers360.com/question-location-of-lpu-phagwara-in-punjab | F11: Demand base | G11: 30,000+ students on a 600-acre campus on GT Road | H11: students | I11: 01 Project Definition; 04 turns ramp | J11: VERIFIED (secondary). Supports the size of the customer pool. | K11: Use LPU official website figures if available.
A12: SRC-08 | B12: Income Tax Act - concessional corporate rate (Sec. 115BAA) | C12: Statute | D12: Current | E12: https://incometax.gov.in | F12: Tax rate | G12: 22% + surcharge + cess = 25.17% | H12: % | I12: 04 Assumptions E | J12: STANDARD STATUTORY RATE. Well established; not re-opened during this session. | K12: Confirm on incometax.gov.in.
A13: SRC-09 | B13: FSSAI licence fee schedule / shop registration | C13: Regulator | D13: Current | E13: https://foscos.fssai.gov.in | F13: Licence costs | G13: ~₹30,000 setup; ~₹5,000 yearly renewals (estimate) | H13: ₹ | I13: 04 Assumptions D, G | J13: ESTIMATE. Fees to be confirmed on the FSSAI FoSCoS portal. | K13: Check FoSCoS fee page (5 minutes).
A14: SRC-10 | B14: Restaurant industry cost benchmarks (food cost 28-35% of sales; supplier credit 7-15 days) | C14: Industry rule of thumb | D14: General | E14: General industry practice | F14: Variable cost %, inventory and payable days | G14: 32% ingredients + 4% packaging | H14: % of sales | I14: 04 Assumptions B, F | J14: ESTIMATE (benchmark). Tested via sensitivity on variable cost. | K14: Cite a restaurant-industry report if available.
A15: SRC-11 | B15: Typical supplier price ranges (e.g. IndiaMART listings) for café equipment, furniture, fit-out | C15: Supplier listings | D15: General | E15: https://www.indiamart.com | F15: Capex items | G15: Equipment ₹8L, furniture ₹3.5L, interiors ₹6L, POS ₹0.8L | H15: ₹ | I15: 04 Assumptions G, H | J15: ESTIMATE. Not a formal quotation. | K15: One supplier quote or IndiaMART screenshot would upgrade this.
... A19: SRC-15 | B19: Bank MSME term-loan terms (SBI / PNB) | C19: Bank | D19: General | E19: https://sbi.co.in | F19: Debt share, tenor, spread | G19: 50% debt; 5 years; repo + ~4.75% | H19: - | I19: 04 Assumptions I | J19: ESTIMATE. Loan terms are indicative. | K19: Check SBI MSME loan page.

Sheet 03_AI_Research_Log
A1: 03 · AI Research Log
A2: Usage Of AI
A4: Date | B4: Tool | C4: Prompt / question | D4: AI output used | E4: Original source used to verify | F4: Verified fact | G4: Correction / rejection | H4: Final use in model
A5: 30/09/2026 | B5: Claude (Anthropic) | C5: Explain the FIN 545 assignment and suggest a project. | D5: Summary of the brief; project options (EV charging hub, café). | E5: Assignment PDF supplied by faculty. | F5: Rubric weights add up to 30 marks. | G5: EV charging hub rejected as too complex for the time available. | H5: Project choice: café near LPU.
A6: 30/09/2026 | B6: Claude (Anthropic) | C6: Find Punjab minimum wages effective 2026. | D6: Daily minimum wages by skill level. | E6: WageIndicator page reproducing the Punjab notification. | F6: Unskilled ₹518.69, semi-skilled ₹553.19, skilled ₹592.84 per day from 1 May 2026. | G6: None. | H6: Salary levels in 04_Assumptions.
A7: 30/09/2026 | B7: Claude (Anthropic) | C7: Find PSPCL / PSERC commercial electricity tariff. | D7: Tariff ranges for commercial consumers. | E7: The Tribune and Babushahi reports on PSERC tariff orders. | F7: Commercial ₹6.89-7.75/kWh in FY2025-26; non-residential charges reduced in FY2026-27. | G7: ₹7.2/kWh chosen as a conservative all-in rate. | H7: Electricity cost in 08_Cost_Model.
A8: 30/09/2026 | B8: Claude (Anthropic) | C8: Find RBI repo rate and 10-year G-Sec yield. | D8: Repo 5.25%; 10Y yield ~7.1%; CPI 4.82%. | E8: 5paisa/Akashvani (RBI policy); Trading Economics. | F8: Figures confirmed as of Aug-Sep 2026. | G8: Loan spread and equity premium are the modeller's estimates, not AI facts. | H8: Interest rate, risk-free rate, price growth.

Sheet 04_Assumptions
A1: 04 · Assumption Register (control centre)
A2: Assumptions set for the business model
A4: ID | B4: Assumption | C4: Value | D4: Unit | E4: Period | F4: Source ID | G4: Rationale / estimation method | H4: What happens if it is wrong | I4: Status
A5: A. OPERATING DRIVERS
A6: A02 | B6: Seating capacity | C6: 30 | D6: seats | E6: at launch | F6: SRC-12 | G6: Shop of ~750 sq ft at ~25 sq ft per seat (kitchen/counter take the rest). Capacity is the physical ceiling on customers. | H6: Fewer seats = lower revenue ceiling; more seats = higher rent/fit-out | I6: Estimate
A7: A03 | B7: Operating days per year | C7: 330 | D7: days/yr | E7: annual | F7: SRC-12 | G7: Open ~330 days; closed for festivals and some semester-break days near a university campus. | H7: Volume moves 1:1 with days | I7: Estimate
A8: A04 | B8: Average bill per customer (ex-GST) | C8: 160 | D8: ₹/customer | E8: Year 1 | F8: SRC-13 | G8: Typical campus-café ticket: a hot/cold beverage plus a snack or a meal combo. To confirm against menus of nearby cafés on Zomato/Swiggy. | H8: Revenue moves 1:1 (tested in sensitivity) | I8: Estimate
A9: A05 | B9: Annual price increase (Year 2-5) | C9: 0.05 | D9: % p.a. | E9: Year 2-5 | F9: SRC-06 | G9: Menu prices assumed to rise roughly with inflation. India CPI was 4.82% in Aug 2026 and RBI projects 4.6% for FY27. | H9: Lower price growth reduces later-year revenue | I9: Partly verified
A10: B. VARIABLE COSTS (change with number of customers)
A11: A07 | B11: Food & beverage ingredients | C11: 0.32 | D11: % of sales | E11: annual | F11: SRC-10 | G11: Cafés commonly run food cost near 28-35% of sales; 32% chosen. Rule-of-thumb benchmark, stress-tested in sensitivity. | H11: Each 1 pt of margin = 1% of sales in profit | I11: Estimate
A12: A08 | B12: Packaging & consumables | C12: 0.04 | D12: % of sales | E12: annual | F12: SRC-10 | G12: Cups, napkins, takeaway boxes, cleaning consumables. | H12: Small | I12: Estimate
A13: C. STAFF (fixed cost)
A14: A10 | B14: Cook / chef - headcount | C14: 1 | D14: persons | E14: annual | F14: SRC-01 | G14: One skilled cook for kitchen operations. | H14: Understaffing hurts service | I14: Estimate
A15: A11 | B15: Cook / chef - salary | C15: 22000 | D15: ₹/month | E15: monthly | F15: SRC-01 | G15: Above Punjab skilled minimum wage (₹592.84/day ≈ ₹15,400/month for 26 days). | H15: Payroll is the biggest fixed cost | I15: Floor verified; level estimated
A16: A12 | B16: Counter / service staff - headcount | C16: 2 | D16: persons | E16: annual | F16: SRC-01 | G16: Two staff for counter and table service. | I16: Estimate
A17: A13 | B17: Counter / service staff - salary | C17: 15000 | D17: ₹/month | E17: monthly | F17: SRC-01 | G17: Above semi-skilled minimum wage (₹553.19/day ≈ ₹14,400/month). | I17: Floor verified; level estimated
A18: A14 | B18: Helper - headcount | C18: 1 | D18: persons | E18: annual | F18: SRC-01 | G18: Cleaning and dishwashing. | I18: Estimate
A19: A15 | B19: Helper - salary | C19: 13500 | D19: ₹/month | E19: monthly | F19: SRC-01 | G19: At unskilled minimum wage (₹518.69/day ≈ ₹13,500/month). | I19: Floor verified
A20: A16 | B20: Manager - headcount | C20: 1 | D20: persons | E20: annual | F20: SRC-01 | G20: One manager to run the shop (owner-operator paid a salary). | I20: Estimate
A21: A17 | B21: Manager - salary | C21: 25000 | D21: ₹/month | E21: monthly | F21: SRC-01 | G21: Market-level manager pay for a small café. | I21: Estimate
A22: A18 | B22: Total base monthly payroll (calculated) | C22: =C14*C15+C16*C17+C18*C19+C20*C21 -> 90500 | D22: ₹/month | E22: monthly | F22: - | G22: Headcount × salary, summed. Formula, not an input. | I22: Calculated
A23: A19 | B23: Annual salary increase | C23: 0.06 | D23: % p.a. | E23: Year 2-5 | F23: SRC-06 | G23: Slightly above inflation to retain staff and follow minimum-wage revisions. | I23: Estimate
A24: A20 | B24: Statutory & other staff on-costs | C24: 0.08 | D24: % of salary | E24: annual | F24: SRC-01 | G24: PF/ESI, bonus and uniforms, added on top of salaries. | I24: Estimate
A25: D. RENT, UTILITIES & OTHER FIXED COSTS
A26: A22 | B26: Shop area rented | C26: 750 | D26: sq ft | E26: annual | F26: SRC-12 | G26: Matches 30-seat layout. | I26: Estimate
A27: A23 | B27: Rent per sq ft | C27: 90 | D27: ₹/sq ft/month | E27: monthly | F27: SRC-12 | G27: Commercial shop rent on GT Road / near campus. Replace with an actual listing or landlord quote if you can. | H27: Rent is ~25% of fixed costs | I27: Estimate
A28: A24 | B28: Annual rent escalation | C28: 0.05 | D28: % p.a. | E28: Year 2-5 | F28: SRC-12 | G28: Typical lease escalation of ~5% a year. | I28: Estimate
A29: A25 | B29: Electricity use at Year-1 volume | C29: 2000 | D29: kWh/month | E29: monthly | F29: SRC-02 | G29: AC, refrigeration, lighting, kitchen appliances. | I29: Estimate
A30: A26 | B30: Share of electricity that is fixed (rest moves with customers) | C30: 0.6 | D30: % | E30: annual | F30: SRC-02 | G30: Semi-variable cost: fridges and lighting are constant, cooking/AC load rises with customers. | I30: Estimate
A31: A27 | B31: Electricity tariff (commercial, all-in) | C31: 7.2 | D31: ₹/kWh | E31: Year 1 | F31: SRC-02 | G31: PSERC commercial tariff was ₹6.89-7.75/kWh in FY2025-26; FY2026-27 order reduced non-residential energy charges. ₹7.2 is a conservative all-in figure. | H31: Small effect | I31: Verified range
A32: A28 | B32: LPG, water & other kitchen utilities | C32: 6000 | D32: ₹/month | E32: monthly | F32: SRC-12 | G32: Cooking gas and water. | I32: Estimate
A33: A29 | B33: Marketing & promotions | C33: 8000 | D33: ₹/month | E33: monthly | F33: SRC-13 | G33: Social media, student offers, loyalty discounts. Fixed budget. | I33: Estimate
A34: A30 | B34: Insurance | C34: 25000 | D34: ₹/year | E34: annual | F34: SRC-12 | G34: Fire and contents cover. | I34: Estimate
A35: A31 | B35: Other fixed costs (accounting, POS subscription, cleaning) | C35: 6000 | D35: ₹/month | E35: monthly | F35: SRC-12 | G35: Bookkeeping, software, misc. | I35: Estimate
A36: A32 | B36: Licence renewals (FSSAI, shop registration) | C36: 5000 | D36: ₹/year | E36: annual | F36: SRC-09 | G36: Annual renewal of food-safety and shop licences. | I36: Estimate
A37: A33 | B37: Maintenance (% of equipment, furniture & tech cost) | C37: 0.03 | D37: % of cost | E37: annual | F37: SRC-11 | G37: Repairs and servicing; kept separate from capex. | I37: Estimate
A38: A34 | B38: General cost inflation (utilities, marketing, insurance, other) | C38: 0.05 | D38: % p.a. | E38: Year 2-5 | F38: SRC-06 | G38: In line with CPI trend. | I38: Partly verified
A39: E. TAX
A40: A36 | B40: Corporate income tax rate | C40: 0.2517 | D40: % | E40: annual | F40: SRC-08 | G40: Domestic company under the concessional regime (22% + surcharge + cess = 25.17%). Losses are not carried forward (conservative). | H40: Tax only bites once profits appear | I40: Statutory
A41: F. WORKING CAPITAL
A42: A38 | B42: Receivable days | C42: 2 | D42: days | E42: annual | F42: SRC-13 | G42: Most customers pay at once (cash/UPI); UPI/card settlement lags about 2 days. | I42: Estimate
A43: A39 | B43: Inventory days (on variable cost) | C43: 7 | D43: days | E43: annual | F43: SRC-10 | G43: Fresh ingredients bought weekly. | I43: Estimate
A44: A40 | B44: Payable days (on variable cost) | C44: 10 | D44: days | E44: annual | F44: SRC-10 | G44: Suppliers typically allow 7-15 days for small buyers. | I44: Estimate
A45: A41 | B45: Opening cash buffer (months of Year-1 operating cost) | C45: 2 | D45: months | E45: Year 0 | F45: SRC-10 | G45: Cash needed to cover running costs while sales ramp up. Derived from the cost model, not chosen arbitrarily. | H45: A thin buffer risks running out of cash | I45: Estimate
A46: G. YEAR-0 INVESTMENT
A47: A43 | B47: Kitchen equipment (coffee machine, grill, fridges, etc.) | C47: 800000 | D47: ₹ | E47: Year 0 | F47: SRC-11 | G47: Typical supplier price range for a small café kitchen. Get one quotation if possible. | H47: Changes capex and depreciation | I47: Estimate
A48: A44 | B48: Furniture & fixtures (30 seats) | C48: 350000 | D48: ₹ | E48: Year 0 | F48: SRC-11 | G48: ~₹11,700 per seat incl. counters and shelves. | I48: Estimate
A49: A45 | B49: Interiors / fit-out | C49: 600000 | D49: ₹ | E49: Year 0 | F49: SRC-11 | G49: ~₹800 per sq ft for lighting, flooring, painting, signage. | I49: Estimate
A50: A46 | B50: POS, software & CCTV | C50: 80000 | D50: ₹ | E50: Year 0 | F50: SRC-11 | G50: Billing system and basic security. | I50: Estimate
A51: A47 | B51: Licences & registration | C51: 30000 | D51: ₹ | E51: Year 0 | F51: SRC-09 | G51: FSSAI, shop and establishment, fire/health approvals. | I51: Estimate
A52: A48 | B52: Pre-opening & setup costs | C52: 120000 | D52: ₹ | E52: Year 0 | F52: SRC-13 | G52: Staff training, launch marketing, opening stock. | I52: Estimate
A53: A49 | B53: Contingency (% of the six items above) | C53: 0.05 | D53: % | E53: Year 0 | F53: SRC-11 | G53: Small allowance for cost overruns; applied only to the listed items. | I53: Estimate
A54: A50 | B54: Refundable security deposit (months of rent) | C54: 3 | D54: months | E54: Year 0 | F54: SRC-12 | G54: Standard 2-3 months of rent; refunded at end of the lease. | I54: Estimate
A55: H. USEFUL LIVES (straight-line)
A56: A52 | B56: Kitchen equipment | C56: 8 | D56: years | E56: - | F56: SRC-11 | G56: Typical commercial equipment life. | I56: Estimate
A57: A53 | B57: Furniture & fixtures | C57: 8 | D57: years | E57: - | F57: SRC-11 | I57: Estimate
A58: A54 | B58: Interiors / fit-out | C58: 5 | D58: years | E58: - | F58: SRC-12 | G58: Limited to the assumed 5-year lease. | I58: Estimate
A59: A55 | B59: POS / technology | C59: 4 | D59: years | E59: - | F59: SRC-11 | G59: Shorter tech life. | I59: Estimate
A60: A56 | B60: Pre-operative expenses (amortised) | C60: 5 | D60: years | E60: - | F60: SRC-11 | G60: Licences, pre-opening and contingency are capitalised and written off over 5 years. | I60: Estimate
A61: I. FUNDING
A62: A58 | B62: Debt share of total investment | C62: 0.5 | D62: % | E62: Year 0 | F62: SRC-15 | G62: Half funded by a bank/MSME term loan, half by promoter equity. | H62: More debt = more interest risk | I62: Estimate
A63: A59 | B63: Interest rate on term loan | C63: 0.1 | D63: % p.a. | E63: annual | F63: SRC-04 | G63: RBI repo rate is 5.25%; small-business loans price at repo plus a spread of roughly 4-5%. Confirm with a bank. | I63: Repo verified; spread estimated
A64: A60 | B64: Loan tenor (equal annual principal repayments) | C64: 5 | D64: years | E64: - | F64: SRC-15 | G64: Repayment starts in Year 1. | I64: Estimate
A65: J. TERMINAL VALUE
A66: A62 | B66: Resale value of equipment/furniture at end of Year 5 (% of book value) | C66: 0.25 | D66: % | E66: Year 5 | F66: SRC-11 | G66: Second-hand café equipment sells at a steep discount. Conservative. | H66: Small effect | I66: Estimate
A67: K. DISCOUNT RATE (required return)
A68: A64 | B68: Risk-free rate (10-year G-Sec yield) | C68: 0.071 | D68: % | E68: Sep 2026 | F68: SRC-05 | G68: India 10-year government bond yield was about 7.1% in mid-September 2026. | I68: Verified
A69: A65 | B69: Business risk (beta) | C69: 1 | D69: x | E69: - | F69: SRC-14 | G69: Set to market average; a single-outlet café is at least as risky as the market. | I69: Estimate
A70: A66 | B70: Equity risk premium | C70: 0.07 | D70: % | E70: - | F70: SRC-14 | G70: Extra return investors demand for equity over government bonds in India. | I70: Estimate
A71: A67 | B71: Small-business / start-up premium | C71: 0.05 | D71: % | E71: - | F71: SRC-14 | G71: Added because this is a new, unlisted, single-outlet business. | I71: Estimate
A72: A68 | B72: Cost of equity (calculated) | C72: =C68+C69*C70+C71 -> 0.191 | D72: % | E72: - | F72: - | G72: Risk-free + beta × equity risk premium + start-up premium. | I72: Calculated
A73: A69 | B73: After-tax cost of debt (calculated) | C73: =C63*(1-C40) -> 0.07483 | D73: % | E73: - | F73: - | G73: Loan interest rate × (1 − tax rate). | I73: Calculated
A74: A70 | B74: Discount rate used for NPV (WACC, calculated) | C74: =(1-C62)*C72+C62*C73 -> 0.132915 | D74: % | E74: - | F74: - | G74: Weighted average of equity and debt costs using the funding mix. | H74: Higher rate = lower NPV | I74: Calculated
A76: L. YEAR-WISE DRIVER: seat turns per day (how many times each seat is used per day)
B77: Year | C77: Year 1 | D77: Year 2 | E77: Year 3 | F77: Year 4 | G77: Year 5
B78: Seat turns per day | C78: 2.5 | D78: 3 | E78: 3.5 | F78: 3.8 | G78: 4
B79: Basis (SRC-12 / SRC-07): A new café fills slowly; turns ramp from 2.5 to 4.0 as the outlet becomes known to about 30,000+ LPU students and staff (SRC-07). One turn = one customer group occupies a seat, pays and leaves. Estimate; if wrong, revenue moves in direct proportion (tested in sensitivity as "volume").

Sheet 05_Operating_Drivers
A1: 05 · Operating Drivers
A2: Revenue is built from physical capacity: seats × how often each seat is used × average bill
A4: ₹ (unless stated) | B4: Type / unit | C4: Year 0 | D4: Year 1 | E4: Year 2 | F4: Year 3 | G4: Year 4 | H4: Year 5
A5: Year index (used in formulas) | C5: 0 | D5: 1 | E5: 2 | F5: 3 | G5: 4 | H5: 5
A6: Units: seating capacity | B6: seats | D6: ='04_Assumptions'!$C$6 -> 30 | E6: ='04_Assumptions'!$C$6 -> 30 | F6: ='04_Assumptions'!$C$6 -> 30 | G6: ='04_Assumptions'!$C$6 -> 30 | H6: ='04_Assumptions'!$C$6 -> 30
A7: Seat turns per day | B7: turns/day | D7: ='04_Assumptions'!$C$78 -> 2.5 | E7: ='04_Assumptions'!$D$78 -> 3 | F7: ='04_Assumptions'!$E$78 -> 3.5 | G7: ='04_Assumptions'!$F$78 -> 3.8 | H7: ='04_Assumptions'!$G$78 -> 4
A8: Operating days | B8: days | D8: ='04_Assumptions'!$C$7 -> 330 | E8: ='04_Assumptions'!$C$7 -> 330 | F8: ='04_Assumptions'!$C$7 -> 330 | G8: ='04_Assumptions'!$C$7 -> 330 | H8: ='04_Assumptions'!$C$7 -> 330
A9: Transactions per unit per year (fills per seat) | B9: per seat/yr | D9: =D7*D8 -> 825 | E9: =E7*E8 -> 990 | F9: =F7*F8 -> 1155 | G9: =G7*G8 -> 1254 | H9: =H7*H8 -> 1320
A10: Average price per transaction (bill) | B10: ₹/customer | D10: ='04_Assumptions'!$C$8*(1+'04_Assumptions'!$C$9)^(D$5-1) -> 160 | E10: ='04_Assumptions'!$C$8*(1+'04_Assumptions'!$C$9)^(E$5-1) -> 168 | F10: ='04_Assumptions'!$C$8*(1+'04_Assumptions'!$C$9)^(F$5-1) -> 176.4 | G10: ='04_Assumptions'!$C$8*(1+'04_Assumptions'!$C$9)^(G$5-1) -> 185.22 | H10: ='04_Assumptions'!$C$8*(1+'04_Assumptions'!$C$9)^(H$5-1) -> 194.481
A11: Total customers per year | B11: customers | D11: =D6*D9 -> 24750 | E11: =E6*E9 -> 29700 | F11: =F6*F9 -> 34650 | G11: =G6*G9 -> 37620 | H11: =H6*H9 -> 39600
A12: Customers per day | B12: customers/day | D12: =D11/D8 -> 75 | E12: =E11/E8 -> 90 | F12: =F11/F8 -> 105 | G12: =G11/G8 -> 114 | H12: =H11/H8 -> 120
A14: Unit of economics: ONE CUSTOMER VISIT (a paid bill). Customers = seats × turns/day × days open.

Sheet 06_Investment_Funding
A1: 06 · Year-0 Investment & Funding
A2: Cash committed before the café opens. Funding must equal investment.
A4: Investment item | B4: ₹ | C4: Basis
A5: Kitchen equipment | B5: ='04_Assumptions'!$C$47 -> 800000 | C5: Assumption G
A6: Furniture & fixtures | B6: ='04_Assumptions'!$C$48 -> 350000 | C6: Assumption G
A7: Interiors / fit-out | B7: ='04_Assumptions'!$C$49 -> 600000 | C7: Assumption G
A8: POS, software & CCTV | B8: ='04_Assumptions'!$C$50 -> 80000 | C8: Assumption G
A9: Licences & registration | B9: ='04_Assumptions'!$C$51 -> 30000 | C9: Assumption G
A10: Pre-opening & setup | B10: ='04_Assumptions'!$C$52 -> 120000 | C10: Assumption G
A11: Contingency | B11: ='04_Assumptions'!$C$53*SUM(B5:B10) -> 99000 | C11: 5% of items above
A12: Fixed assets & pre-operative expenses | B12: =SUM(B5:B11) -> 2079000
A13: Refundable security deposit | B13: ='04_Assumptions'!$C$54*'04_Assumptions'!$C$26*'04_Assumptions'!$C$27 -> 202500 | C13: Months of Year-1 rent (refunded at end of lease)
A14: Initial working capital (opening cash buffer) | B14: ='04_Assumptions'!$C$45/12*('08_Cost_Model'!D9+'08_Cost_Model'!D21) -> 648030 | C14: Months of Year-1 operating cost from 08_Cost_Model (not arbitrary)
A15: TOTAL INITIAL INVESTMENT (Year 0) | B15: =B12+B13+B14 -> 2929530
A18: FUNDING | B18: ₹ | C18: Basis
A19: Bank term loan (debt) | B19: ='04_Assumptions'!$C$62*B15 -> 1464765 | C19: Debt share × total investment
A20: Promoter equity | B20: =B15-B19 -> 1464765 | C20: Balancing: total investment − debt
A21: Total funding | B21: =B19+B20 -> 2929530
A22: Check: funding − investment (must be 0) | B22: =ROUND(B21-B15,2) -> 0
A24: Split used for depreciation: physical assets = rows 5-8; pre-operative = licences + pre-opening + contingency.

Sheet 07_Revenue_Model
A1: 07 · Driver-Based Revenue Model
A2: Revenue = Units × Transactions per unit × Average price (all linked from 05_Operating_Drivers).
A4: ₹ (unless stated) | B4: Type / unit | C4: Year 0 | D4: Year 1 | E4: Year 2 | F4: Year 3 | G4: Year 4 | H4: Year 5
A5: Year index (used in formulas) | C5: 0 | D5: 1 | E5: 2 | F5: 3 | G5: 4 | H5: 5
A6: Units (seats) | B6: seats | D6: ='05_Operating_Drivers'!D6 -> 30 | E6: ='05_Operating_Drivers'!E6 -> 30 | F6: ='05_Operating_Drivers'!F6 -> 30 | G6: ='05_Operating_Drivers'!G6 -> 30 | H6: ='05_Operating_Drivers'!H6 -> 30
A7: Transactions per unit per year | B7: per seat | D7: ='05_Operating_Drivers'!D9 -> 825 | E7: ='05_Operating_Drivers'!E9 -> 990 | F7: ='05_Operating_Drivers'!F9 -> 1155 | G7: ='05_Operating_Drivers'!G9 -> 1254 | H7: ='05_Operating_Drivers'!H9 -> 1320
A8: Average price per transaction | B8: ₹ | D8: ='05_Operating_Drivers'!D10 -> 160 | E8: ='05_Operating_Drivers'!E10 -> 168 | F8: ='05_Operating_Drivers'!F10 -> 176.4 | G8: ='05_Operating_Drivers'!G10 -> 185.22 | H8: ='05_Operating_Drivers'!H10 -> 194.481
A9: Core revenue (café sales) | B9: ₹ | D9: =D6*D7*D8 -> 3960000 | E9: =E6*E7*E8 -> 4989600 | F9: =F6*F7*F8 -> 6112260 | G9: =G6*G7*G8 -> 6967976.4 | H9: =H6*H7*H8 -> 7701447.6
A10: Other revenue (none assumed) | B10: ₹ | D10: 0 | E10: 0 | F10: 0 | G10: 0 | H10: 0 | I10: No second revenue stream assumed.
A11: Total revenue (ex-GST) | B11: ₹ | D11: =D9+D10 -> 3960000 | E11: =E9+E10 -> 4989600 | F11: =F9+F10 -> 6112260 | G11: =G9+G10 -> 6967976.4 | H11: =H9+H10 -> 7701447.6
A12: Revenue growth | B12: % | E12: =E11/D11-1 -> 0.26 | F12: =F11/E11-1 -> 0.225 | G12: =G11/F11-1 -> 0.14 | H12: =H11/G11-1 -> 0.10526316

Sheet 08_Cost_Model
A1: 08 · Driver-Based Cost Model
A2: Variable, fixed and semi-variable costs kept separate. Variable = % of sales; fixed = documented amounts; electricity is semi-variable.
A4: ₹ (unless stated) | B4: Type / unit | C4: Year 0 | D4: Year 1 | E4: Year 2 | F4: Year 3 | G4: Year 4 | H4: Year 5
A5: Year index (used in formulas) | C5: 0 | D5: 1 | E5: 2 | F5: 3 | G5: 4 | H5: 5
A6: Customers per year | B6: driver | D6: ='05_Operating_Drivers'!D11 -> 24750 | E6: ='05_Operating_Drivers'!E11 -> 29700 | F6: ='05_Operating_Drivers'!F11 -> 34650 | G6: ='05_Operating_Drivers'!G11 -> 37620 | H6: ='05_Operating_Drivers'!H11 -> 39600
A7: Ingredients (F&B cost) | B7: Variable | D7: ='07_Revenue_Model'!D11*'04_Assumptions'!$C$11 -> 1267200 | E7: ='07_Revenue_Model'!E11*'04_Assumptions'!$C$11 -> 1596672 | F7: ='07_Revenue_Model'!F11*'04_Assumptions'!$C$11 -> 1955923.2 | G7: ='07_Revenue_Model'!G11*'04_Assumptions'!$C$11 -> 2229752.4 | H7: ='07_Revenue_Model'!H11*'04_Assumptions'!$C$11 -> 2464463.2
A8: Packaging & consumables | B8: Variable | D8: ='07_Revenue_Model'!D11*'04_Assumptions'!$C$12 -> 158400 | E8: ='07_Revenue_Model'!E11*'04_Assumptions'!$C$12 -> 199584 | F8: ='07_Revenue_Model'!F11*'04_Assumptions'!$C$12 -> 244490.4 | G8: ='07_Revenue_Model'!G11*'04_Assumptions'!$C$12 -> 278719.06 | H8: ='07_Revenue_Model'!H11*'04_Assumptions'!$C$12 -> 308057.9
A9: Total variable cost | B9: Variable | D9: =D7+D8 -> 1425600 | E9: =E7+E8 -> 1796256 | F9: =F7+F8 -> 2200413.6 | G9: =G7+G8 -> 2508471.5 | H9: =H7+H8 -> 2772521.1
A10: Variable cost per customer | B10: ₹/customer | D10: =D9/D6 -> 57.6 | E10: =E9/E6 -> 60.48 | F10: =F9/F6 -> 63.504 | G10: =G9/G6 -> 66.6792 | H10: =H9/H6 -> 70.01316
A12: Salaries incl. on-costs | B12: Fixed | D12: ='04_Assumptions'!$C$22*12*(1+'04_Assumptions'!$C$23)^(D$5-1)*(1+'04_Assumptions'!$C$24) -> 1172880 | E12: ='04_Assumptions'!$C$22*12*(1+'04_Assumptions'!$C$23)^(E$5-1)*(1+'04_Assumptions'!$C$24) -> 1243252.8 | F12: ='04_Assumptions'!$C$22*12*(1+'04_Assumptions'!$C$23)^(F$5-1)*(1+'04_Assumptions'!$C$24) -> 1317848 | G12: ='04_Assumptions'!$C$22*12*(1+'04_Assumptions'!$C$23)^(G$5-1)*(1+'04_Assumptions'!$C$24) -> 1396918.8 | H12: ='04_Assumptions'!$C$22*12*(1+'04_Assumptions'!$C$23)^(H$5-1)*(1+'04_Assumptions'!$C$24) -> 1480734 | I12: Headcount × salary × 12, +6% p.a., +8% on-costs
A13: Rent | B13: Fixed | D13: ='04_Assumptions'!$C$26*'04_Assumptions'!$C$27*12*(1+'04_Assumptions'!$C$28)^(D$5-1) -> 810000 | E13: ='04_Assumptions'!$C$26*'04_Assumptions'!$C$27*12*(1+'04_Assumptions'!$C$28)^(E$5-1) -> 850500 | F13: ='04_Assumptions'!$C$26*'04_Assumptions'!$C$27*12*(1+'04_Assumptions'!$C$28)^(F$5-1) -> 893025 | G13: ='04_Assumptions'!$C$26*'04_Assumptions'!$C$27*12*(1+'04_Assumptions'!$C$28)^(G$5-1) -> 937676.25 | H13: ='04_Assumptions'!$C$26*'04_Assumptions'!$C$27*12*(1+'04_Assumptions'!$C$28)^(H$5-1) -> 984560.06 | I13: Area × rate × 12, +5% p.a.
A14: Electricity | B14: Semi-variable | D14: ='04_Assumptions'!$C$29*('04_Assumptions'!$C$30+(1-'04_Assumptions'!$C$30)*D6/$D6)*'04_Assumptions'!$C$31*12*(1+'04_Assumptions'!$C$38)^(D$5-1) -> 172800 | E14: ='04_Assumptions'!$C$29*('04_Assumptions'!$C$30+(1-'04_Assumptions'!$C$30)*E6/$D6)*'04_Assumptions'!$C$31*12*(1+'04_Assumptions'!$C$38)^(E$5-1) -> 195955.2 | F14: ='04_Assumptions'!$C$29*('04_Assumptions'!$C$30+(1-'04_Assumptions'!$C$30)*F6/$D6)*'04_Assumptions'!$C$31*12*(1+'04_Assumptions'!$C$38)^(F$5-1) -> 220993.92 | G14: ='04_Assumptions'!$C$29*('04_Assumptions'!$C$30+(1-'04_Assumptions'!$C$30)*G6/$D6)*'04_Assumptions'!$C$31*12*(1+'04_Assumptions'!$C$38)^(G$5-1) -> 241645.42 | H14: ='04_Assumptions'!$C$29*('04_Assumptions'!$C$30+(1-'04_Assumptions'!$C$30)*H6/$D6)*'04_Assumptions'!$C$31*12*(1+'04_Assumptions'!$C$38)^(H$5-1) -> 260448.96 | I14: 60% fixed + 40% moves with customers
A15: LPG, water & kitchen utilities | B15: Fixed | D15: ='04_Assumptions'!$C$32*12*(1+'04_Assumptions'!$C$38)^(D$5-1) -> 72000 | E15: ='04_Assumptions'!$C$32*12*(1+'04_Assumptions'!$C$38)^(E$5-1) -> 75600 | F15: ='04_Assumptions'!$C$32*12*(1+'04_Assumptions'!$C$38)^(F$5-1) -> 79380 | G15: ='04_Assumptions'!$C$32*12*(1+'04_Assumptions'!$C$38)^(G$5-1) -> 83349 | H15: ='04_Assumptions'!$C$32*12*(1+'04_Assumptions'!$C$38)^(H$5-1) -> 87516.45
A16: Marketing | B16: Fixed | D16: ='04_Assumptions'!$C$33*12*(1+'04_Assumptions'!$C$38)^(D$5-1) -> 96000 | E16: ='04_Assumptions'!$C$33*12*(1+'04_Assumptions'!$C$38)^(E$5-1) -> 100800 | F16: ='04_Assumptions'!$C$33*12*(1+'04_Assumptions'!$C$38)^(F$5-1) -> 105840 | G16: ='04_Assumptions'!$C$33*12*(1+'04_Assumptions'!$C$38)^(G$5-1) -> 111132 | H16: ='04_Assumptions'!$C$33*12*(1+'04_Assumptions'!$C$38)^(H$5-1) -> 116688.6
A17: Insurance | B17: Fixed | D17: ='04_Assumptions'!$C$34*(1+'04_Assumptions'!$C$38)^(D$5-1) -> 25000 | E17: ='04_Assumptions'!$C$34*(1+'04_Assumptions'!$C$38)^(E$5-1) -> 26250 | F17: ='04_Assumptions'!$C$34*(1+'04_Assumptions'!$C$38)^(F$5-1) -> 27562.5 | G17: ='04_Assumptions'!$C$34*(1+'04_Assumptions'!$C$38)^(G$5-1) -> 28940.625 | H17: ='04_Assumptions'!$C$34*(1+'04_Assumptions'!$C$38)^(H$5-1) -> 30387.656
A18: Maintenance | B18: Fixed | D18: ='04_Assumptions'!$C$37*('04_Assumptions'!$C$47+'04_Assumptions'!$C$48+'04_Assumptions'!$C$50)*(1+'04_Assumptions'!$C$38)^(D$5-1) -> 36900 | E18: ='04_Assumptions'!$C$37*('04_Assumptions'!$C$47+'04_Assumptions'!$C$48+'04_Assumptions'!$C$50)*(1+'04_Assumptions'!$C$38)^(E$5-1) -> 38745 | F18: ='04_Assumptions'!$C$37*('04_Assumptions'!$C$47+'04_Assumptions'!$C$48+'04_Assumptions'!$C$50)*(1+'04_Assumptions'!$C$38)^(F$5-1) -> 40682.25 | G18: ='04_Assumptions'!$C$37*('04_Assumptions'!$C$47+'04_Assumptions'!$C$48+'04_Assumptions'!$C$50)*(1+'04_Assumptions'!$C$38)^(G$5-1) -> 42716.363 | H18: ='04_Assumptions'!$C$37*('04_Assumptions'!$C$47+'04_Assumptions'!$C$48+'04_Assumptions'!$C$50)*(1+'04_Assumptions'!$C$38)^(H$5-1) -> 44852.181
A19: Licence renewals | B19: Fixed | D19: ='04_Assumptions'!$C$36*(1+'04_Assumptions'!$C$38)^(D$5-1) -> 5000 | E19: ='04_Assumptions'!$C$36*(1+'04_Assumptions'!$C$38)^(E$5-1) -> 5250 | F19: ='04_Assumptions'!$C$36*(1+'04_Assumptions'!$C$38)^(F$5-1) -> 5512.5 | G19: ='04_Assumptions'!$C$36*(1+'04_Assumptions'!$C$38)^(G$5-1) -> 5788.125 | H19: ='04_Assumptions'!$C$36*(1+'04_Assumptions'!$C$38)^(H$5-1) -> 6077.5312
A20: Other fixed costs | B20: Fixed | D20: ='04_Assumptions'!$C$35*12*(1+'04_Assumptions'!$C$38)^(D$5-1) -> 72000 | E20: ='04_Assumptions'!$C$35*12*(1+'04_Assumptions'!$C$38)^(E$5-1) -> 75600 | F20: ='04_Assumptions'!$C$35*12*(1+'04_Assumptions'!$C$38)^(F$5-1) -> 79380 | G20: ='04_Assumptions'!$C$35*12*(1+'04_Assumptions'!$C$38)^(G$5-1) -> 83349 | H20: ='04_Assumptions'!$C$35*12*(1+'04_Assumptions'!$C$38)^(H$5-1) -> 87516.45
A21: Total fixed & semi-variable operating cost | B21: Fixed | D21: =SUM(D12:D20) -> 2462580 | E21: =SUM(E12:E20) -> 2611953 | F21: =SUM(F12:F20) -> 2770224.1 | G21: =SUM(G12:G20) -> 2931515.6 | H21: =SUM(H12:H20) -> 3098781.9
A22: Total operating cost (before depreciation & interest) | D22: =D9+D21 -> 3888180 | E22: =E9+E21 -> 4408209 | F22: =F9+F21 -> 4970637.7 | G22: =G9+G21 -> 5439987.1 | H22: =H9+H21 -> 5871303
A24: Quality test: if revenue doubled, ingredients and packaging double, electricity rises partly (40% moves), and salaries/rent stay fixed.

Sheet 09_Assets_Depreciation
A1: 09 · Asset Register & Depreciation
A2: (Straight-line depreciation. Depreciation is non-cash: it reduces profit and tax but is added back in cash flow.)
A4: Asset | B4: Initial cost ₹ | C4: Useful life (yrs) | D4: Method | E4: Annual depreciation | F4: Year-1 NBV | G4: Year-5 NBV | H4: Source / basis
A5: Kitchen equipment | B5: ='06_Investment_Funding'!B5 -> 800000 | C5: ='04_Assumptions'!$C$56 -> 8 | D5: Straight-line | E5: =B5/C5 -> 100000 | F5: =B5-E5 -> 700000 | G5: =MAX(0,B5-E5*MIN(5,C5)) -> 300000 | H5: SRC-11
A6: Furniture & fixtures | B6: ='06_Investment_Funding'!B6 -> 350000 | C6: ='04_Assumptions'!$C$57 -> 8 | D6: Straight-line | E6: =B6/C6 -> 43750 | F6: =B6-E6 -> 306250 | G6: =MAX(0,B6-E6*MIN(5,C6)) -> 131250 | H6: SRC-11
A7: Interiors / fit-out | B7: ='06_Investment_Funding'!B7 -> 600000 | C7: ='04_Assumptions'!$C$58 -> 5 | D7: Straight-line | E7: =B7/C7 -> 120000 | F7: =B7-E7 -> 480000 | G7: =MAX(0,B7-E7*MIN(5,C7)) -> 0 | H7: SRC-12
A8: POS, software & CCTV | B8: ='06_Investment_Funding'!B8 -> 80000 | C8: ='04_Assumptions'!$C$59 -> 4 | D8: Straight-line | E8: =B8/C8 -> 20000 | F8: =B8-E8 -> 60000 | G8: =MAX(0,B8-E8*MIN(5,C8)) -> 0 | H8: SRC-11
A9: Pre-operative expenses (licences, pre-opening, contingency) | B9: ='06_Investment_Funding'!B9+'06_Investment_Funding'!B10+'06_Investment_Funding'!B11 -> 249000 | C9: ='04_Assumptions'!$C$60 -> 5 | D9: Straight-line | E9: =B9/C9 -> 49800 | F9: =B9-E9 -> 199200 | G9: =MAX(0,B9-E9*MIN(5,C9)) -> 0 | H9: SRC-11
A12: Year-wise schedule
A13: ₹ | B13: Type | C13: Year 0 | D13: Year 1 | E13: Year 2 | F13: Year 3 | G13: Year 4 | H13: Year 5
A14: Year index | C14: 0 | D14: 1 | E14: 2 | F14: 3 | G14: 4 | H14: 5
A15: Depreciation - Kitchen equipment | B15: Expense | D15: =IF(D$14<=$C$5,$B$5/$C$5,0) -> 100000 | E15: =IF(E$14<=$C$5,$B$5/$C$5,0) -> 100000 | F15: =IF(F$14<=$C$5,$B$5/$C$5,0) -> 100000 | G15: =IF(G$14<=$C$5,$B$5/$C$5,0) -> 100000 | H15: =IF(H$14<=$C$5,$B$5/$C$5,0) -> 100000
A16: Depreciation - Furniture & fixtures | B16: Expense | D16: =IF(D$14<=$C$6,$B$6/$C$6,0) -> 43750 | E16: =IF(E$14<=$C$6,$B$6/$C$6,0) -> 43750 | F16: =IF(F$14<=$C$6,$B$6/$C$6,0) -> 43750 | G16: =IF(G$14<=$C$6,$B$6/$C$6,0) -> 43750 | H16: =IF(H$14<=$C$6,$B$6/$C$6,0) -> 43750
A17: Depreciation - Interiors / fit-out | B17: Expense | D17: =IF(D$14<=$C$7,$B$7/$C$7,0) -> 120000 | E17: =IF(E$14<=$C$7,$B$7/$C$7,0) -> 120000 | F17: =IF(F$14<=$C$7,$B$7/$C$7,0) -> 120000 | G17: =IF(G$14<=$C$7,$B$7/$C$7,0) -> 120000 | H17: =IF(H$14<=$C$7,$B$7/$C$7,0) -> 120000
A18: Depreciation - POS, software & CCTV | B18: Expense | D18: =IF(D$14<=$C$8,$B$8/$C$8,0) -> 20000 | E18: =IF(E$14<=$C$8,$B$8/$C$8,0) -> 20000 | F18: =IF(F$14<=$C$8,$B$8/$C$8,0) -> 20000 | G18: =IF(G$14<=$C$8,$B$8/$C$8,0) -> 20000 | H18: =IF(H$14<=$C$8,$B$8/$C$8,0) -> 0
A19: Depreciation - Pre-operative expenses | B19: Expense | D19: =IF(D$14<=$C$9,$B$9/$C$9,0) -> 49800 | E19: =IF(E$14<=$C$9,$B$9/$C$9,0) -> 49800 | F19: =IF(F$14<=$C$9,$B$9/$C$9,0) -> 49800 | G19: =IF(G$14<=$C$9,$B$9/$C$9,0) -> 49800 | H19: =IF(H$14<=$C$9,$B$9/$C$9,0) -> 49800
A20: Total depreciation & amortisation | B20: Expense | D20: =SUM(D15:D19) -> 333550 | E20: =SUM(E15:E19) -> 333550 | F20: =SUM(F15:F19) -> 333550 | G20: =SUM(G15:G19) -> 333550 | H20: =SUM(H15:H19) -> 313550
A22: Net book value - Kitchen equipment | C22: =$B$5 -> 800000 | D22: =C22-D15 -> 700000 | E22: =D22-E15 -> 600000 | F22: =E22-F15 -> 500000 | G22: =F22-G15 -> 400000 | H22: =G22-H15 -> 300000
A23: Net book value - Furniture & fixtures | C23: =$B$6 -> 350000 | D23: =C23-D16 -> 306250 | E23: =D23-E16 -> 262500 | F23: =E23-F16 -> 218750 | G23: =F23-G16 -> 175000 | H23: =G23-H16 -> 131250
A24: Net book value - Interiors / fit-out | C24: =$B$7 -> 600000 | D24: =C24-D17 -> 480000 | E24: =D24-E17 -> 360000 | F24: =E24-F17 -> 240000 | G24: =F24-G17 -> 120000 | H24: =G24-H17 -> 0
A25: Net book value - POS, software & CCTV | C25: =$B$8 -> 80000 | D25: =C25-D18 -> 60000 | E25: =D25-E18 -> 40000 | F25: =E25-F18 -> 20000 | G25: =F25-G18 -> 0 | H25: =G25-H18 -> 0
A26: Net book value - Pre-operative expenses | C26: =$B$9 -> 249000 | D26: =C26-D19 -> 199200 | E26: =D26-E19 -> 149400 | F26: =E26-F19 -> 99600 | G26: =F26-G19 -> 49800 | H26: =G26-H19 -> 0
A27: Total net book value | C27: =SUM(C22:C26) -> 2079000 | D27: =SUM(D22:D26) -> 1745450 | E27: =SUM(E22:E26) -> 1411900 | F27: =SUM(F22:F26) -> 1078350 | G27: =SUM(G22:G26) -> 744800 | H27: =SUM(H22:H26) -> 431250
A28: NBV of physical assets (used for salvage) | C28: =SUM(C22:C25) -> 1830000 | D28: =SUM(D22:D25) -> 1546250 | E28: =SUM(E22:E25) -> 1262500 | F28: =SUM(F22:F25) -> 978750 | G28: =SUM(G22:G25) -> 695000 | H28: =SUM(H22:H25) -> 431250

Sheet 10_Debt_Schedule
A1: 10 · Debt Schedule
A2: Term loan with equal annual principal repayments. Interest is charged on the opening balance.
A4: ₹ (unless stated) | B4: Type / unit | C4: Year 0 | D4: Year 1 | E4: Year 2 | F4: Year 3 | G4: Year 4 | H4: Year 5
A5: Year index (used in formulas) | C5: 0 | D5: 1 | E5: 2 | F5: 3 | G5: 4 | H5: 5
A6: Opening debt | C6: 0 | D6: =C9 -> 1464765 | E6: =D9 -> 1171812 | F6: =E9 -> 878859 | G6: =F9 -> 585906 | H6: =G9 -> 292953
A7: New borrowing | C7: ='06_Investment_Funding'!B19 -> 1464765 | D7: 0 | E7: 0 | F7: 0 | G7: 0 | H7: 0
A8: Principal repayment | C8: 0 | D8: =MIN(D6,$C$7/'04_Assumptions'!$C$64) -> 292953 | E8: =MIN(E6,$C$7/'04_Assumptions'!$C$64) -> 292953 | F8: =MIN(F6,$C$7/'04_Assumptions'!$C$64) -> 292953 | G8: =MIN(G6,$C$7/'04_Assumptions'!$C$64) -> 292953 | H8: =MIN(H6,$C$7/'04_Assumptions'!$C$64) -> 292953
A9: Closing debt | C9: =C6+C7-C8 -> 1464765 | D9: =D6+D7-D8 -> 1171812 | E9: =E6+E7-E8 -> 878859 | F9: =F6+F7-F8 -> 585906 | G9: =G6+G7-G8 -> 292953 | H9: =H6+H7-H8 -> 0
A10: Interest rate | D10: ='04_Assumptions'!$C$63 -> 0.1 | E10: ='04_Assumptions'!$C$63 -> 0.1 | F10: ='04_Assumptions'!$C$63 -> 0.1 | G10: ='04_Assumptions'!$C$63 -> 0.1 | H10: ='04_Assumptions'!$C$63 -> 0.1
A11: Interest expense | D11: =D6*D10 -> 146476.5 | E11: =E6*E10 -> 117181.2 | F11: =F6*F10 -> 87885.9 | G11: =G6*G10 -> 58590.6 | H11: =H6*H10 -> 29295.3

Sheet 11_Working_Capital
A1: 11 · Working Capital
A2: Receivables, inventory and payables linked to the operating cycle. An increase in NWC uses cash.
A4: ₹ (unless stated) | B4: Type / unit | C4: Year 0 | D4: Year 1 | E4: Year 2 | F4: Year 3 | G4: Year 4 | H4: Year 5
A5: Year index (used in formulas) | C5: 0 | D5: 1 | E5: 2 | F5: 3 | G5: 4 | H5: 5
A6: Revenue | B6: link | D6: ='07_Revenue_Model'!D11 -> 3960000 | E6: ='07_Revenue_Model'!E11 -> 4989600 | F6: ='07_Revenue_Model'!F11 -> 6112260 | G6: ='07_Revenue_Model'!G11 -> 6967976.4 | H6: ='07_Revenue_Model'!H11 -> 7701447.6
A7: Variable cost | B7: link | D7: ='08_Cost_Model'!D9 -> 1425600 | E7: ='08_Cost_Model'!E9 -> 1796256 | F7: ='08_Cost_Model'!F9 -> 2200413.6 | G7: ='08_Cost_Model'!G9 -> 2508471.5 | H7: ='08_Cost_Model'!H9 -> 2772521.1
A8: Receivable days | B8: days | D8: ='04_Assumptions'!$C$42 -> 2 | E8: ='04_Assumptions'!$C$42 -> 2 | F8: ='04_Assumptions'!$C$42 -> 2 | G8: ='04_Assumptions'!$C$42 -> 2 | H8: ='04_Assumptions'!$C$42 -> 2
A9: Inventory days | B9: days | D9: ='04_Assumptions'!$C$43 -> 7 | E9: ='04_Assumptions'!$C$43 -> 7 | F9: ='04_Assumptions'!$C$43 -> 7 | G9: ='04_Assumptions'!$C$43 -> 7 | H9: ='04_Assumptions'!$C$43 -> 7
A10: Payable days | B10: days | D10: ='04_Assumptions'!$C$44 -> 10 | E10: ='04_Assumptions'!$C$44 -> 10 | F10: ='04_Assumptions'!$C$44 -> 10 | G10: ='04_Assumptions'!$C$44 -> 10 | H10: ='04_Assumptions'!$C$44 -> 10
A11: Accounts receivable | B11: Asset | C11: 0 | D11: =D6*D8/365 -> 21698.63 | E11: =E6*E8/365 -> 27340.274 | F11: =F6*F8/365 -> 33491.836 | G11: =G6*G8/365 -> 38180.693 | H11: =H6*H8/365 -> 42199.713
A12: Inventory | B12: Asset | C12: 0 | D12: =D7*D9/365 -> 27340.274 | E12: =E7*E9/365 -> 34448.745 | F12: =F7*F9/365 -> 42199.713 | G12: =G7*G9/365 -> 48107.673 | H12: =H7*H9/365 -> 53171.638
A13: Accounts payable | B13: Liability | C13: 0 | D13: =D7*D10/365 -> 39057.534 | E13: =E7*E10/365 -> 49212.493 | F13: =F7*F10/365 -> 60285.304 | G13: =G7*G10/365 -> 68725.247 | H13: =H7*H10/365 -> 75959.483
A14: Net working capital (AR + Inventory − AP) | C14: 0 | D14: =D11+D12-D13 -> 9981.3699 | E14: =E11+E12-E13 -> 12576.526 | F14: =F11+F12-F13 -> 15406.244 | G14: =G11+G12-G13 -> 17563.119 | H14: =H11+H12-H13 -> 19411.868
A15: Change in NWC (increase = cash used) | D15: =D14-C14 -> 9981.3699 | E15: =E14-D14 -> 2595.1562 | F15: =F14-E14 -> 2829.7184 | G15: =G14-F14 -> 2156.8742 | H15: =H14-G14 -> 1848.7493

Sheet 12_Income_Statement
A1: 12 · Projected Income Statement
A2: All figures linked from the schedules; nothing typed twice. Tax = 25.17% of positive profit only (no loss carry-forward).
A4: ₹ (unless stated) | B4: Type / unit | C4: Year 0 | D4: Year 1 | E4: Year 2 | F4: Year 3 | G4: Year 4 | H4: Year 5
A5: Year index (used in formulas) | C5: 0 | D5: 1 | E5: 2 | F5: 3 | G5: 4 | H5: 5
A6: Revenue | D6: ='07_Revenue_Model'!D11 -> 3960000 | E6: ='07_Revenue_Model'!E11 -> 4989600 | F6: ='07_Revenue_Model'!F11 -> 6112260 | G6: ='07_Revenue_Model'!G11 -> 6967976.4 | H6: ='07_Revenue_Model'!H11 -> 7701447.6
A7: Variable cost | D7: ='08_Cost_Model'!D9 -> 1425600 | E7: ='08_Cost_Model'!E9 -> 1796256 | F7: ='08_Cost_Model'!F9 -> 2200413.6 | G7: ='08_Cost_Model'!G9 -> 2508471.5 | H7: ='08_Cost_Model'!H9 -> 2772521.1
A8: Gross contribution | D8: =D6-D7 -> 2534400 | E8: =E6-E7 -> 3193344 | F8: =F6-F7 -> 3911846.4 | G8: =G6-G7 -> 4459504.9 | H8: =H6-H7 -> 4928926.5
A9: Fixed operating cost | D9: ='08_Cost_Model'!D21 -> 2462580 | E9: ='08_Cost_Model'!E21 -> 2611953 | F9: ='08_Cost_Model'!F21 -> 2770224.1 | G9: ='08_Cost_Model'!G21 -> 2931515.6 | H9: ='08_Cost_Model'!H21 -> 3098781.9
A10: EBITDA | D10: =D8-D9 -> 71820 | E10: =E8-E9 -> 581391 | F10: =F8-F9 -> 1141622.3 | G10: =G8-G9 -> 1527989.3 | H10: =H8-H9 -> 1830144.6
A11: Depreciation & amortisation | D11: ='09_Assets_Depreciation'!D20 -> 333550 | E11: ='09_Assets_Depreciation'!E20 -> 333550 | F11: ='09_Assets_Depreciation'!F20 -> 333550 | G11: ='09_Assets_Depreciation'!G20 -> 333550 | H11: ='09_Assets_Depreciation'!H20 -> 313550
A12: EBIT | D12: =D10-D11 -> -261730 | E12: =E10-E11 -> 247841 | F12: =F10-F11 -> 808072.26 | G12: =G10-G11 -> 1194439.3 | H12: =H10-H11 -> 1516594.6
A13: Interest expense | D13: ='10_Debt_Schedule'!D11 -> 146476.5 | E13: ='10_Debt_Schedule'!E11 -> 117181.2 | F13: ='10_Debt_Schedule'!F11 -> 87885.9 | G13: ='10_Debt_Schedule'!G11 -> 58590.6 | H13: ='10_Debt_Schedule'!H11 -> 29295.3
A14: Profit before tax | D14: =D12-D13 -> -408206.5 | E14: =E12-E13 -> 130659.8 | F14: =F12-F13 -> 720186.36 | G14: =G12-G13 -> 1135848.7 | H14: =H12-H13 -> 1487299.3
A15: Tax | D15: =MAX(0,D14)*'04_Assumptions'!$C$40 -> 0 | E15: =MAX(0,E14)*'04_Assumptions'!$C$40 -> 32887.072 | F15: =MAX(0,F14)*'04_Assumptions'!$C$40 -> 181270.91 | G15: =MAX(0,G14)*'04_Assumptions'!$C$40 -> 285893.11 | H15: =MAX(0,H14)*'04_Assumptions'!$C$40 -> 374353.23
A16: Net profit | D16: =D14-D15 -> -408206.5 | E16: =E14-E15 -> 97772.728 | F16: =F14-F15 -> 538915.45 | G16: =G14-G15 -> 849955.56 | H16: =H14-H15 -> 1112946.1
A17: EBITDA margin | D17: =D10/D6 -> 0.018136364 | E17: =E10/E6 -> 0.11652056 | F17: =F10/F6 -> 0.1867758 | G17: =G10/G6 -> 0.21928738 | H17: =H10/H6 -> 0.23763644
A18: Net profit margin | D18: =D16/D6 -> -0.10308245 | E18: =E16/E6 -> 0.019595304 | F18: =F16/F6 -> 0.088169589 | G18: =G16/G6 -> 0.12198026 | H18: =H16/H6 -> 0.14451128

Sheet 13_Cash_Flow
A1: 13 · Projected Cash Flow Statement
A2: Operating + investing + financing = net change in cash
A4: ₹ (unless stated) | B4: Type / unit | C4: Year 0 | D4: Year 1 | E4: Year 2 | F4: Year 3 | G4: Year 4 | H4: Year 5
A5: Year index (used in formulas) | C5: 0 | D5: 1 | E5: 2 | F5: 3 | G5: 4 | H5: 5
A6: Net profit | C6: 0 | D6: ='12_Income_Statement'!D16 -> -408206.5 | E6: ='12_Income_Statement'!E16 -> 97772.728 | F6: ='12_Income_Statement'!F16 -> 538915.45 | G6: ='12_Income_Statement'!G16 -> 849955.56 | H6: ='12_Income_Statement'!H16 -> 1112946.1
A7: Add: depreciation & amortisation (non-cash) | C7: 0 | D7: ='12_Income_Statement'!D11 -> 333550 | E7: ='12_Income_Statement'!E11 -> 333550 | F7: ='12_Income_Statement'!F11 -> 333550 | G7: ='12_Income_Statement'!G11 -> 333550 | H7: ='12_Income_Statement'!H11 -> 313550
A8: Less: increase in net working capital | C8: 0 | D8: -9981.3699 | E8: -2595.1562 | F8: -2829.7184 | G8: -2156.8742 | H8: -1848.7493
A9: Cash flow from operations | C9: =SUM(C6:C8) -> 0 | D9: =SUM(D6:D8) -> -84637.87 | E9: =SUM(E6:E8) -> 428727.57 | F9: =SUM(F6:F8) -> 869635.74 | G9: =SUM(G6:G8) -> 1181348.7 | H9: =SUM(H6:H8) -> 1424647.3
A11: Capex, pre-operative costs & security deposit | C11: =-('06_Investment_Funding'!B12+'06_Investment_Funding'!B13) -> -2281500 | D11: 0 | E11: 0 | F11: 0 | G11: 0 | H11: 0
A12: Cash flow from investing | C12: =C11 -> -2281500 | D12: =D11 -> 0 | E12: =E11 -> 0 | F12: =F11 -> 0 | G12: =G11 -> 0 | H12: =H11 -> 0
A14: New borrowing | C14: ='10_Debt_Schedule'!C7 -> 1464765 | D14: 0 | E14: 0 | F14: 0 | G14: 0 | H14: 0
A15: Promoter equity introduced | C15: ='06_Investment_Funding'!B20 -> 1464765 | D15: 0 | E15: 0 | F15: 0 | G15: 0 | H15: 0
A16: Principal repayment | C16: 0 | D16: -292953 | E16: -292953 | F16: -292953 | G16: -292953 | H16: -292953
A17: Cash flow from financing | C17: =SUM(C14:C16) -> 2929530 | D17: =SUM(D14:D16) -> -292953 | E17: =SUM(E14:E16) -> -292953 | F17: =SUM(F14:F16) -> -292953 | G17: =SUM(G14:G16) -> -292953 | H17: =SUM(H14:H16) -> -292953
A19: Net change in cash | C19: =C9+C12+C17 -> 648030 | D19: =D9+D12+D17 -> -377590.87 | E19: =E9+E12+E17 -> 135774.57 | F19: =F9+F12+F17 -> 576682.74 | G19: =G9+G12+G17 -> 888395.68 | H19: =H9+H12+H17 -> 1131694.3
A20: Opening cash | C20: 0 | D20: =C21 -> 648030 | E20: =D21 -> 270439.13 | F20: =E21 -> 406213.7 | G20: =F21 -> 982896.44 | H20: =G21 -> 1871292.1
A21: Closing cash | C21: =C20+C19 -> 648030 | D21: =D20+D19 -> 270439.13 | E21: =E20+E19 -> 406213.7 | F21: =F20+F19 -> 982896.44 | G21: =G20+G19 -> 1871292.1 | H21: =H20+H19 -> 3002986.4

Sheet 14_Balance_Sheet
A1: 14 · Projected Balance Sheet
A2: Control check: Total assets − (liabilities + equity) must be zero in every year.
A4: ₹ (unless stated) | B4: Type / unit | C4: Year 0 | D4: Year 1 | E4: Year 2 | F4: Year 3 | G4: Year 4 | H4: Year 5
A5: Year index (used in formulas) | C5: 0 | D5: 1 | E5: 2 | F5: 3 | G5: 4 | H5: 5
A6: Net fixed assets & unamortised pre-operative costs | C6: ='09_Assets_Depreciation'!C27 -> 2079000 | D6: ='09_Assets_Depreciation'!D27 -> 1745450 | E6: ='09_Assets_Depreciation'!E27 -> 1411900 | F6: ='09_Assets_Depreciation'!F27 -> 1078350 | G6: ='09_Assets_Depreciation'!G27 -> 744800 | H6: ='09_Assets_Depreciation'!H27 -> 431250
A7: Refundable security deposit | C7: ='06_Investment_Funding'!B13 -> 202500 | D7: ='06_Investment_Funding'!B13 -> 202500 | E7: ='06_Investment_Funding'!B13 -> 202500 | F7: ='06_Investment_Funding'!B13 -> 202500 | G7: ='06_Investment_Funding'!B13 -> 202500 | H7: ='06_Investment_Funding'!B13 -> 202500
A8: Accounts receivable | C8: ='11_Working_Capital'!C11 -> 0 | D8: ='11_Working_Capital'!D11 -> 21698.63 | E8: ='11_Working_Capital'!E11 -> 27340.274 | F8: ='11_Working_Capital'!F11 -> 33491.836 | G8: ='11_Working_Capital'!G11 -> 38180.693 | H8: ='11_Working_Capital'!H11 -> 42199.713
A9: Inventory | C9: ='11_Working_Capital'!C12 -> 0 | D9: ='11_Working_Capital'!D12 -> 27340.274 | E9: ='11_Working_Capital'!E12 -> 34448.745 | F9: ='11_Working_Capital'!F12 -> 42199.713 | G9: ='11_Working_Capital'!G12 -> 48107.673 | H9: ='11_Working_Capital'!H12 -> 53171.638
A10: Cash | C10: ='13_Cash_Flow'!C21 -> 648030 | D10: ='13_Cash_Flow'!D21 -> 270439.13 | E10: ='13_Cash_Flow'!E21 -> 406213.7 | F10: ='13_Cash_Flow'!F21 -> 982896.44 | G10: ='13_Cash_Flow'!G21 -> 1871292.1 | H10: ='13_Cash_Flow'!H21 -> 3002986.4
A11: TOTAL ASSETS | C11: =SUM(C6:C10) -> 2929530 | D11: =SUM(D6:D10) -> 2267428 | E11: =SUM(E6:E10) -> 2082402.7 | F11: =SUM(F6:F10) -> 2339438 | G11: =SUM(G6:G10) -> 2904880.5 | H11: =SUM(H6:H10) -> 3732107.8
A13: Accounts payable | C13: ='11_Working_Capital'!C13 -> 0 | D13: ='11_Working_Capital'!D13 -> 39057.534 | E13: ='11_Working_Capital'!E13 -> 49212.493 | F13: ='11_Working_Capital'!F13 -> 60285.304 | G13: ='11_Working_Capital'!G13 -> 68725.247 | H13: ='11_Working_Capital'!H13 -> 75959.483
A14: Bank term loan | C14: ='10_Debt_Schedule'!C9 -> 1464765 | D14: ='10_Debt_Schedule'!D9 -> 1171812 | E14: ='10_Debt_Schedule'!E9 -> 878859 | F14: ='10_Debt_Schedule'!F9 -> 585906 | G14: ='10_Debt_Schedule'!G9 -> 292953 | H14: ='10_Debt_Schedule'!H9 -> 0
A15: TOTAL LIABILITIES | C15: =C13+C14 -> 1464765 | D15: =D13+D14 -> 1210869.5 | E15: =E13+E14 -> 928071.49 | F15: =F13+F14 -> 646191.3 | G15: =G13+G14 -> 361678.25 | H15: =H13+H14 -> 75959.483
A17: Promoter equity (share capital) | C17: ='06_Investment_Funding'!B20 -> 1464765 | D17: ='06_Investment_Funding'!B20 -> 1464765 | E17: ='06_Investment_Funding'!B20 -> 1464765 | F17: ='06_Investment_Funding'!B20 -> 1464765 | G17: ='06_Investment_Funding'!B20 -> 1464765 | H17: ='06_Investment_Funding'!B20 -> 1464765
A18: Retained earnings | C18: 0 | D18: =C18+'12_Income_Statement'!D16 -> -408206.5 | E18: =D18+'12_Income_Statement'!E16 -> -310433.77 | F18: =E18+'12_Income_Statement'!F16 -> 228481.68 | G18: =F18+'12_Income_Statement'!G16 -> 1078437.2 | H18: =G18+'12_Income_Statement'!H16 -> 2191383.3
A19: TOTAL EQUITY | C19: =C17+C18 -> 1464765 | D19: =D17+D18 -> 1056558.5 | E19: =E17+E18 -> 1154331.2 | F19: =F17+F18 -> 1693246.7 | G19: =G17+G18 -> 2543202.2 | H19: =H17+H18 -> 3656148.3
A20: TOTAL LIABILITIES & EQUITY | C20: =C15+C19 -> 2929530 | D20: =D15+D19 -> 2267428 | E20: =E15+E19 -> 2082402.7 | F20: =F15+F19 -> 2339438 | G20: =G15+G19 -> 2904880.5 | H20: =H15+H19 -> 3732107.8
A22: BALANCE CHECK (must be 0) | C22: =ROUND(C11-C20,2) -> 0 | D22: =ROUND(D11-D20,2) -> 0 | E22: =ROUND(E11-E20,2) -> 0 | F22: =ROUND(F11-F20,2) -> 0 | G22: =ROUND(G11-G20,2) -> 0 | H22: =ROUND(H11-H20,2) -> 0

Sheet 15_Project_FCF
A1: 15 · Project Free Cash Flow
A2: Measures the café as a project, independent of how it is financed: NO interest, NO loan drawdown, NO principal repayment.
A4: ₹ (unless stated) | B4: Type / unit | C4: Year 0 | D4: Year 1 | E4: Year 2 | F4: Year 3 | G4: Year 4 | H4: Year 5
A5: Year index (used in formulas) | C5: 0 | D5: 1 | E5: 2 | F5: 3 | G5: 4 | H5: 5
A6: EBIT (operating profit) | D6: ='12_Income_Statement'!D12 -> -261730 | E6: ='12_Income_Statement'!E12 -> 247841 | F6: ='12_Income_Statement'!F12 -> 808072.26 | G6: ='12_Income_Statement'!G12 -> 1194439.3 | H6: ='12_Income_Statement'!H12 -> 1516594.6
A7: Tax on EBIT | D7: =MAX(0,D6)*'04_Assumptions'!$C$40 -> 0 | E7: =MAX(0,E6)*'04_Assumptions'!$C$40 -> 62381.58 | F7: =MAX(0,F6)*'04_Assumptions'!$C$40 -> 203391.79 | G7: =MAX(0,G6)*'04_Assumptions'!$C$40 -> 300640.36 | H7: =MAX(0,H6)*'04_Assumptions'!$C$40 -> 381726.86
A8: NOPAT (EBIT − tax on EBIT) | D8: =D6-D7 -> -261730 | E8: =E6-E7 -> 185459.42 | F8: =F6-F7 -> 604680.47 | G8: =G6-G7 -> 893798.9 | H8: =H6-H7 -> 1134867.7
A9: Add: depreciation & amortisation | D9: ='12_Income_Statement'!D11 -> 333550 | E9: ='12_Income_Statement'!E11 -> 333550 | F9: ='12_Income_Statement'!F11 -> 333550 | G9: ='12_Income_Statement'!G11 -> 333550 | H9: ='12_Income_Statement'!H11 -> 313550
A10: Less: capex & pre-operative costs | C10: -2079000 | D10: 0 | E10: 0 | F10: 0 | G10: 0 | H10: 0
A11: Less: security deposit paid | C11: -202500 | D11: 0 | E11: 0 | F11: 0 | G11: 0 | H11: 0
A12: Less: initial working capital (cash buffer) | C12: -648030 | D12: 0 | E12: 0 | F12: 0 | G12: 0 | H12: 0
A13: Less: increase in NWC | D13: -9981.3699 | E13: -2595.1562 | F13: -2829.7184 | G13: -2156.8742 | H13: -1848.7493
A14: After-tax salvage value of assets (Year 5) | C14: 0 | D14: 0 | E14: 0 | F14: 0 | G14: 0 | H14: ='04_Assumptions'!$C$66*'09_Assets_Depreciation'!H28-'04_Assumptions'!$C$40*MAX(0,'04_Assumptions'!$C$66*'09_Assets_Depreciation'!H28-'09_Assets_Depreciation'!H28) -> 107812.5
A15: Release of initial working capital (Year 5) | C15: 0 | D15: 0 | E15: 0 | F15: 0 | G15: 0 | H15: ='06_Investment_Funding'!B14 -> 648030
A16: Refund of security deposit (Year 5) | C16: 0 | D16: 0 | E16: 0 | F16: 0 | G16: 0 | H16: ='06_Investment_Funding'!B13 -> 202500
A17: PROJECT FREE CASH FLOW | C17: =C8+C9+SUM(C10:C16) -> -2929530 | D17: =D8+D9+SUM(D10:D16) -> 61838.63 | E17: =E8+E9+SUM(E10:E16) -> 516414.26 | F17: =F8+F9+SUM(F10:F16) -> 935400.76 | G17: =G8+G9+SUM(G10:G16) -> 1225192 | H17: =H8+H9+SUM(H10:H16) -> 2404911.5
A18: Cumulative Project FCF | C18: =C17 -> -2929530 | D18: =C18+D17 -> -2867691.4 | E18: =D18+E17 -> -2351277.1 | F18: =E18+F17 -> -1415876.4 | G18: =F18+G17 -> -190684.32 | H18: =G18+H17 -> 2214227.2
A20: Salvage: resale = 25% of physical-asset book value at Year 5; tax on any gain is zero because resale is below book value.

Sheet 16_Appraisal
A1: 16 · Investment Appraisal (NPV, IRR, Payback)
A2: All metrics use the SAME Project FCF series from 15_Project_FCF.
A4: ₹ (unless stated) | B4: Type / unit | C4: Year 0 | D4: Year 1 | E4: Year 2 | F4: Year 3 | G4: Year 4 | H4: Year 5
A5: Year index (used in formulas) | C5: 0 | D5: 1 | E5: 2 | F5: 3 | G5: 4 | H5: 5
A6: Required return (WACC) | C6: ='04_Assumptions'!$C$74 -> 0.132915
A8: Project FCF | C8: ='15_Project_FCF'!C17 -> -2929530 | D8: ='15_Project_FCF'!D17 -> 61838.63 | E8: ='15_Project_FCF'!E17 -> 516414.26 | F8: ='15_Project_FCF'!F17 -> 935400.76 | G8: ='15_Project_FCF'!G17 -> 1225192 | H8: ='15_Project_FCF'!H17 -> 2404911.5
A9: Cumulative Project FCF | C9: =C8 -> -2929530 | D9: =C9+D8 -> -2867691.4 | E9: =D9+E8 -> -2351277.1 | F9: =E9+F8 -> -1415876.4 | G9: =F9+G8 -> -190684.32 | H9: =G9+H8 -> 2214227.2
A10: Discount factor | C10: =1/(1+$C$6)^C$5 -> 1 | D10: =1/(1+$C$6)^D$5 -> 0.88267875 | E10: =1/(1+$C$6)^E$5 -> 0.77912178 | F10: =1/(1+$C$6)^F$5 -> 0.68771424 | G10: =1/(1+$C$6)^G$5 -> 0.60703075 | H10: =1/(1+$C$6)^H$5 -> 0.53581315
A11: Present value of FCF | C11: =C8*C10 -> -2929530 | D11: =D8*D10 -> 54583.645 | E11: =E8*E10 -> 402349.6 | F11: =F8*F10 -> 643288.42 | G11: =G8*G10 -> 743729.24 | H11: =H8*H10 -> 1288583.2
A12: Payback helper (fraction-of-year recovery) | D12: =IF(AND(C9<0,D9>=0),(D$5-1)+(-C9)/D8,0) -> 0 | E12: =IF(AND(D9<0,E9>=0),(E$5-1)+(-D9)/E8,0) -> 0 | F12: =IF(AND(E9<0,F9>=0),(F$5-1)+(-E9)/F8,0) -> 0 | G12: =IF(AND(F9<0,G9>=0),(G$5-1)+(-F9)/G8,0) -> 0 | H12: =IF(AND(G9<0,H9>=0),(H$5-1)+(-G9)/H8,0) -> 4.0792895
A15: NPV (₹) | C15: =C8+NPV(C6,D8:H8) -> 203004.1 | D15: Year-0 FCF + PV of Years 1-5 at the required return
A16: NPV cross-check (sum of PVs) | C16: =SUM(C11:H11) -> 203004.1
A17: Project IRR | C17: =IFERROR(IRR(C8:H8),"n/a") -> 0.15261855
A18: IRR minus required return | C18: =IFERROR(C17-C6,"n/a") -> 0.019703546
A19: Payback period (years) | C19: =IF(SUM(D12:H12)=0,"> 5 yrs",SUM(D12:H12)) -> 4.0792895
A20: Profitability index (PV of inflows ÷ investment) | C20: =1+C15/-C8 -> 1.0692958
A22: BASE-CASE DECISION | C22: =IF(AND(C15>0,ISNUMBER(C17),C17>C6),IF('18_Scenarios'!E12>0,"Invest","Invest with Conditions"),"Do Not Invest") -> Invest with Conditions
A23: Decision rule: "Invest" if NPV>0, IRR>required return AND the pessimistic NPV is also >0; "Invest with Conditions" if only the base case clears the hurdle; else "Do Not Invest".

Sheet 17_Break_Even
A1: 17 · Break-Even & Margin of Safety
A2: How many customers must the café serve to cover its fixed costs?
A4: Year-1 break-even (EBITDA level) | B4: Value
A5: Selling price per customer (Year 1) | B5: ='05_Operating_Drivers'!D10 -> 160
A6: Variable cost per customer (Year 1) | B6: ='08_Cost_Model'!D10 -> 57.6
A7: Contribution per customer | B7: =B5-B6 -> 102.4
A8: Contribution margin % | B8: =B7/B5 -> 0.64
A9: Annual fixed operating costs (Year 1) | B9: ='08_Cost_Model'!D21 -> 2462580
A10: Break-even customers per year | B10: =B9/B7 -> 24048.633
A11: Break-even customers per day | B11: =B10/'05_Operating_Drivers'!D8 -> 72.874645
A12: Break-even revenue per year (₹) | B12: =B10*B5 -> 3847781.2
A13: Projected Year-1 customers | B13: ='05_Operating_Drivers'!D11 -> 24750
A14: Margin of safety (customers) | B14: =B13-B10 -> 701.36719
A15: Margin of safety % | B15: =B14/B13 -> 0.028338068
A16: Break-even seat turns per day | B16: =B10/('05_Operating_Drivers'!D6*'05_Operating_Drivers'!D8) -> 2.4291548
A17: Reading | B17: =IF(B15>=0.25,"Comfortably above break-even",IF(B15>=0,"Only marginally above break-even in Year 1","Below break-even in Year 1 (expected while the café ramps up)")) -> Only marginally above break-even in Year 1
A19: Break-even by year | D19: Year 1 | E19: Year 2 | F19: Year 3 | G19: Year 4 | H19: Year 5
A20: Price per customer | D20: ='05_Operating_Drivers'!D10 -> 160 | E20: ='05_Operating_Drivers'!E10 -> 168 | F20: ='05_Operating_Drivers'!F10 -> 176.4 | G20: ='05_Operating_Drivers'!G10 -> 185.22 | H20: ='05_Operating_Drivers'!H10 -> 194.481
A21: Variable cost per customer | D21: ='08_Cost_Model'!D10 -> 57.6 | E21: ='08_Cost_Model'!E10 -> 60.48 | F21: ='08_Cost_Model'!F10 -> 63.504 | G21: ='08_Cost_Model'!G10 -> 66.6792 | H21: ='08_Cost_Model'!H10 -> 70.01316
A22: Fixed operating cost | D22: ='08_Cost_Model'!D21 -> 2462580 | E22: ='08_Cost_Model'!E21 -> 2611953 | F22: ='08_Cost_Model'!F21 -> 2770224.1 | G22: ='08_Cost_Model'!G21 -> 2931515.6 | H22: ='08_Cost_Model'!H21 -> 3098781.9
A23: Break-even customers per day | D23: =D22/(D20-D21)/'05_Operating_Drivers'!D8 -> 72.874645 | E23: =E22/(E20-E21)/'05_Operating_Drivers'!E8 -> 73.614296 | F23: =F22/(F20-F21)/'05_Operating_Drivers'!F8 -> 74.357095 | G23: =G22/(G20-G21)/'05_Operating_Drivers'!G8 -> 74.939436 | H23: =H22/(H20-H21)/'05_Operating_Drivers'!H8 -> 75.443167
A24: Projected customers per day | D24: ='05_Operating_Drivers'!D12 -> 75 | E24: ='05_Operating_Drivers'!E12 -> 90 | F24: ='05_Operating_Drivers'!F12 -> 105 | G24: ='05_Operating_Drivers'!G12 -> 114 | H24: ='05_Operating_Drivers'!H12 -> 120
A25: Margin of safety % | D25: =(D24-D23)/D24 -> 0.028338068 | E25: =(E24-E23)/E24 -> 0.18206338 | F25: =(F24-F23)/F24 -> 0.29183719 | G25: =(G24-G23)/G24 -> 0.34263653 | H25: =(H24-H23)/H24 -> 0.37130694
A27: Including depreciation and interest (full accounting break-even, Year 1)
A28: Break-even customers per day incl. depreciation & interest | B28: =(B9+'12_Income_Statement'!D11+'12_Income_Statement'!D13)/B7/'05_Operating_Drivers'!D8 -> 87.079975

Sheet 18_Scenarios
A1: 18 · Scenario Analysis
A2: Each scenario re-runs the whole economics (revenue → costs → tax → working capital → FCF → NPV/IRR). Year-0 investment is held at the base case.
A5: Scenario | B5: Volume change | C5: Price change | D5: Variable cost change | E5: Fixed cost change | F5: Justification
A6: Pessimistic | B6: -0.2 | C6: -0.1 | D6: 0.1 | E6: 0.1 | F6: Template downside: weaker footfall (semester break/competitor opening), discounting to win students, ingredient and rent pressure.
A7: Base | B7: 0 | C7: 0 | D7: 0 | E7: 0 | F7: Matches the base model exactly.
A8: Optimistic | B8: 0.2 | C8: 0.1 | D8: -0.05 | E8: -0.05 | F8: Template upside: strong student adoption, premium items, better supplier terms.
A11: Scenario | B11: Year-1 revenue | C11: Year-5 revenue | D11: Year-5 EBITDA | E11: NPV | F11: IRR | G11: Payback (yrs)
A12: Pessimistic | B12: =D23 -> 2851200 | C12: =H23 -> 5545042.3 | D12: =H26 -> -303436.38 | E12: =C37 -> -4892237.1 | F12: =C38 -> n/a | G12: =C39 -> > 5 yrs
A13: Base | B13: =D43 -> 3960000 | C13: =H43 -> 7701447.6 | D13: =H46 -> 1830144.6 | E13: =C57 -> 203004.1 | F13: =C58 -> 0.15261855 | G13: =C59 -> 4.0792895
A14: Optimistic | B14: =D63 -> 5227200 | C14: =H63 -> 10165911 | D14: =H66 -> 4061394 | E14: =C77 -> 4633870.4 | F14: =C78 -> 0.53820595 | G14: =C79 -> 2.1306725
A16: Check: scenario Base NPV − model NPV (must be 0) | E16: =ROUND(E13-'16_Appraisal'!C15,2) -> 0
A17: Greatest damage | B17: =IF(E12<E13,"Pessimistic scenario: NPV falls by ₹"&TEXT(E13-E12,"#,##0")&" versus base","Check inputs") -> Pessimistic scenario: NPV falls by ₹5,095,241 versus base
A18: Note: electricity is treated as fixed in scenarios (its small volume-linked part is ignored); the effect is negligible.
A22: Scenario engine: Pessimistic | C22: Year 0 | D22: Year 1 | E22: Year 2 | F22: Year 3 | G22: Year 4 | H22: Year 5
A23: Revenue | C23: 0 | D23: ='07_Revenue_Model'!D11*(1+$B$6)*(1+$C$6) -> 2851200 | E23: ='07_Revenue_Model'!E11*(1+$B$6)*(1+$C$6) -> 3592512 | F23: ='07_Revenue_Model'!F11*(1+$B$6)*(1+$C$6) -> 4400827.2 | G23: ='07_Revenue_Model'!G11*(1+$B$6)*(1+$C$6) -> 5016943 | H23: ='07_Revenue_Model'!H11*(1+$B$6)*(1+$C$6) -> 5545042.3
A24: Variable cost | C24: 0 | D24: ='08_Cost_Model'!D9*(1+$B$6)*(1+$D$6) -> 1254528 | E24: ='08_Cost_Model'!E9*(1+$B$6)*(1+$D$6) -> 1580705.3 | F24: ='08_Cost_Model'!F9*(1+$B$6)*(1+$D$6) -> 1936364 | G24: ='08_Cost_Model'!G9*(1+$B$6)*(1+$D$6) -> 2207454.9 | H24: ='08_Cost_Model'!H9*(1+$B$6)*(1+$D$6) -> 2439818.6
A25: Fixed operating cost | C25: 0 | D25: ='08_Cost_Model'!D21*(1+$E$6) -> 2708838 | E25: ='08_Cost_Model'!E21*(1+$E$6) -> 2873148.3 | F25: ='08_Cost_Model'!F21*(1+$E$6) -> 3047246.6 | G25: ='08_Cost_Model'!G21*(1+$E$6) -> 3224667.2 | H25: ='08_Cost_Model'!H21*(1+$E$6) -> 3408660
A26: EBITDA | C26: 0 | D26: =D23-D24-D25 -> -1112166 | E26: =E23-E24-E25 -> -861341.58 | F26: =F23-F24-F25 -> -582783.32 | G26: =G23-G24-G25 -> -415179.11 | H26: =H23-H24-H25 -> -303436.38
A27: Depreciation | C27: 0 | D27: ='09_Assets_Depreciation'!D20 -> 333550 | E27: ='09_Assets_Depreciation'!E20 -> 333550 | F27: ='09_Assets_Depreciation'!F20 -> 333550 | G27: ='09_Assets_Depreciation'!G20 -> 333550 | H27: ='09_Assets_Depreciation'!H20 -> 313550
A28: EBIT | C28: 0 | D28: =D26-D27 -> -1445716 | E28: =E26-E27 -> -1194891.6 | F28: =F26-F27 -> -916333.32 | G28: =G26-G27 -> -748729.11 | H28: =H26-H27 -> -616986.38
A29: Tax on EBIT | C29: 0 | D29: =MAX(0,D28)*'04_Assumptions'!$C$40 -> 0 | E29: =MAX(0,E28)*'04_Assumptions'!$C$40 -> 0 | F29: =MAX(0,F28)*'04_Assumptions'!$C$40 -> 0 | G29: =MAX(0,G28)*'04_Assumptions'!$C$40 -> 0 | H29: =MAX(0,H28)*'04_Assumptions'!$C$40 -> 0
A30: NOPAT | C30: 0 | D30: =D28-D29 -> -1445716 | E30: =E28-E29 -> -1194891.6 | F30: =F28-F29 -> -916333.32 | G30: =G28-G29 -> -748729.11 | H30: =H28-H29 -> -616986.38
A31: Net working capital | C31: 0 | D31: =D23*'04_Assumptions'!$C$42/365+D24*'04_Assumptions'!$C$43/365-D24*'04_Assumptions'!$C$44/365 -> 5311.8247 | E31: =E23*'04_Assumptions'!$C$42/365+E24*'04_Assumptions'!$C$43/365-E24*'04_Assumptions'!$C$44/365 -> 6692.8991 | F31: =F23*'04_Assumptions'!$C$42/365+F24*'04_Assumptions'!$C$43/365-F24*'04_Assumptions'!$C$44/365 -> 8198.8014 | G31: =G23*'04_Assumptions'!$C$42/365+G24*'04_Assumptions'!$C$43/365-G24*'04_Assumptions'!$C$44/365 -> 9346.6335 | H31: =H23*'04_Assumptions'!$C$42/365+H24*'04_Assumptions'!$C$43/365-H24*'04_Assumptions'!$C$44/365 -> 10330.49
A32: Change in NWC | C32: 0 | D32: =D31-C31 -> 5311.8247 | E32: =E31-D31 -> 1381.0744 | F32: =F31-E31 -> 1505.9023 | G32: =G31-F31 -> 1147.8322 | H32: =H31-G31 -> 983.85616
A33: Terminal items (Y5) | C33: 0 | D33: 0 | E33: 0 | F33: 0 | G33: 0 | H33: ='15_Project_FCF'!H14+'15_Project_FCF'!H15+'15_Project_FCF'!H16 -> 958342.5
A34: Project FCF | C34: ='15_Project_FCF'!C17 -> -2929530 | D34: =D30+D27-D32+D33 -> -1117477.8 | E34: =E30+E27-E32+E33 -> -862722.65 | F34: =F30+F27-F32+F33 -> -584289.22 | G34: =G30+G27-G32+G33 -> -416326.94 | H34: =H30+H27-H32+H33 -> 653922.27
A35: Cumulative FCF | C35: =C34 -> -2929530 | D35: =C35+D34 -> -4047007.8 | E35: =D35+E34 -> -4909730.5 | F35: =E35+F34 -> -5494019.7 | G35: =F35+G34 -> -5910346.6 | H35: =G35+H34 -> -5256424.4
A36: Payback helper | D36: =IF(AND(C35<0,D35>=0),0+(-C35)/D34,0) -> 0 | E36: =IF(AND(D35<0,E35>=0),1+(-D35)/E34,0) -> 0 | F36: =IF(AND(E35<0,F35>=0),2+(-E35)/F34,0) -> 0 | G36: =IF(AND(F35<0,G35>=0),3+(-F35)/G34,0) -> 0 | H36: =IF(AND(G35<0,H35>=0),4+(-G35)/H34,0) -> 0
A37: NPV | C37: =C34+NPV('04_Assumptions'!$C$74,D34:H34) -> -4892237.1
A38: IRR | C38: =IFERROR(IRR(C34:H34),"n/a") -> n/a
A39: Payback (years) | C39: =IF(SUM(D36:H36)=0,"> 5 yrs",SUM(D36:H36)) -> > 5 yrs
A42: Scenario engine: Base | C42: Year 0 | D42: Year 1 | E42: Year 2 | F42: Year 3 | G42: Year 4 | H42: Year 5
A43: Revenue | C43: 0 | D43: ='07_Revenue_Model'!D11*(1+$B$7)*(1+$C$7) -> 3960000 | E43: ='07_Revenue_Model'!E11*(1+$B$7)*(1+$C$7) -> 4989600 | F43: ='07_Revenue_Model'!F11*(1+$B$7)*(1+$C$7) -> 6112260 | G43: ='07_Revenue_Model'!G11*(1+$B$7)*(1+$C$7) -> 6967976.4 | H43: ='07_Revenue_Model'!H11*(1+$B$7)*(1+$C$7) -> 7701447.6
A44: Variable cost | C44: 0 | D44: ='08_Cost_Model'!D9*(1+$B$7)*(1+$D$7) -> 1425600 | E44: ='08_Cost_Model'!E9*(1+$B$7)*(1+$D$7) -> 1796256 | F44: ='08_Cost_Model'!F9*(1+$B$7)*(1+$D$7) -> 2200413.6 | G44: ='08_Cost_Model'!G9*(1+$B$7)*(1+$D$7) -> 2508471.5 | H44: ='08_Cost_Model'!H9*(1+$B$7)*(1+$D$7) -> 2772521.1
A45: Fixed operating cost | C45: 0 | D45: ='08_Cost_Model'!D21*(1+$E$7) -> 2462580 | E45: ='08_Cost_Model'!E21*(1+$E$7) -> 2611953 | F45: ='08_Cost_Model'!F21*(1+$E$7) -> 2770224.1 | G45: ='08_Cost_Model'!G21*(1+$E$7) -> 2931515.6 | H45: ='08_Cost_Model'!H21*(1+$E$7) -> 3098781.9
A46: EBITDA | C46: 0 | D46: =D43-D44-D45 -> 71820 | E46: =E43-E44-E45 -> 581391 | F46: =F43-F44-F45 -> 1141622.3 | G46: =G43-G44-G45 -> 1527989.3 | H46: =H43-H44-H45 -> 1830144.6
A47: Depreciation | C47: 0 | D47: ='09_Assets_Depreciation'!D20 -> 333550 | E47: ='09_Assets_Depreciation'!E20 -> 333550 | F47: ='09_Assets_Depreciation'!F20 -> 333550 | G47: ='09_Assets_Depreciation'!G20 -> 333550 | H47: ='09_Assets_Depreciation'!H20 -> 313550
A48: EBIT | C48: 0 | D48: =D46-D47 -> -261730 | E48: =E46-E47 -> 247841 | F48: =F46-F47 -> 808072.26 | G48: =G46-G47 -> 1194439.3 | H48: =H46-H47 -> 1516594.6
A49: Tax on EBIT | C49: 0 | D49: =MAX(0,D48)*'04_Assumptions'!$C$40 -> 0 | E49: =MAX(0,E48)*'04_Assumptions'!$C$40 -> 62381.58 | F49: =MAX(0,F48)*'04_Assumptions'!$C$40 -> 203391.79 | G49: =MAX(0,G48)*'04_Assumptions'!$C$40 -> 300640.36 | H49: =MAX(0,H48)*'04_Assumptions'!$C$40 -> 381726.86
A50: NOPAT | C50: 0 | D50: =D48-D49 -> -261730 | E50: =E48-E49 -> 185459.42 | F50: =F48-F49 -> 604680.47 | G50: =G48-G49 -> 893798.9 | H50: =H48-H49 -> 1134867.7
A51: Net working capital | C51: 0 | D51: =D43*'04_Assumptions'!$C$42/365+D44*'04_Assumptions'!$C$43/365-D44*'04_Assumptions'!$C$44/365 -> 9981.3699 | E51: =E43*'04_Assumptions'!$C$42/365+E44*'04_Assumptions'!$C$43/365-E44*'04_Assumptions'!$C$44/365 -> 12576.526 | F51: =F43*'04_Assumptions'!$C$42/365+F44*'04_Assumptions'!$C$43/365-F44*'04_Assumptions'!$C$44/365 -> 15406.244 | G51: =G43*'04_Assumptions'!$C$42/365+G44*'04_Assumptions'!$C$43/365-G44*'04_Assumptions'!$C$44/365 -> 17563.119 | H51: =H43*'04_Assumptions'!$C$42/365+H44*'04_Assumptions'!$C$43/365-H44*'04_Assumptions'!$C$44/365 -> 19411.868
A52: Change in NWC | C52: 0 | D52: =D51-C51 -> 9981.3699 | E52: =E51-D51 -> 2595.1562 | F52: =F51-E51 -> 2829.7184 | G52: =G51-F51 -> 2156.8742 | H52: =H51-G51 -> 1848.7493
A53: Terminal items (Y5) | C53: 0 | D53: 0 | E53: 0 | F53: 0 | G53: 0 | H53: ='15_Project_FCF'!H14+'15_Project_FCF'!H15+'15_Project_FCF'!H16 -> 958342.5
A54: Project FCF | C54: ='15_Project_FCF'!C17 -> -2929530 | D54: =D50+D47-D52+D53 -> 61838.63 | E54: =E50+E47-E52+E53 -> 516414.26 | F54: =F50+F47-F52+F53 -> 935400.76 | G54: =G50+G47-G52+G53 -> 1225192 | H54: =H50+H47-H52+H53 -> 2404911.5
A55: Cumulative FCF | C55: =C54 -> -2929530 | D55: =C55+D54 -> -2867691.4 | E55: =D55+E54 -> -2351277.1 | F55: =E55+F54 -> -1415876.4 | G55: =F55+G54 -> -190684.32 | H55: =G55+H54 -> 2214227.2
A56: Payback helper | D56: =IF(AND(C55<0,D55>=0),0+(-C55)/D54,0) -> 0 | E56: =IF(AND(D55<0,E55>=0),1+(-D55)/E54,0) -> 0 | F56: =IF(AND(E55<0,F55>=0),2+(-E55)/F54,0) -> 0 | G56: =IF(AND(F55<0,G55>=0),3+(-F55)/G54,0) -> 0 | H56: =IF(AND(G55<0,H55>=0),4+(-G55)/H54,0) -> 4.0792895
A57: NPV | C57: =C54+NPV('04_Assumptions'!$C$74,D54:H54) -> 203004.1
A58: IRR | C58: =IFERROR(IRR(C54:H54),"n/a") -> 0.15261855
A59: Payback (years) | C59: =IF(SUM(D56:H56)=0,"> 5 yrs",SUM(D56:H56)) -> 4.0792895
A62: Scenario engine: Optimistic | C62: Year 0 | D62: Year 1 | E62: Year 2 | F62: Year 3 | G62: Year 4 | H62: Year 5
A63: Revenue | C63: 0 | D63: ='07_Revenue_Model'!D11*(1+$B$8)*(1+$C$8) -> 5227200 | E63: ='07_Revenue_Model'!E11*(1+$B$8)*(1+$C$8) -> 6586272 | F63: ='07_Revenue_Model'!F11*(1+$B$8)*(1+$C$8) -> 8068183.2 | G63: ='07_Revenue_Model'!G11*(1+$B$8)*(1+$C$8) -> 9197728.8 | H63: ='07_Revenue_Model'!H11*(1+$B$8)*(1+$C$8) -> 10165911
A64: Variable cost | C64: 0 | D64: ='08_Cost_Model'!D9*(1+$B$8)*(1+$D$8) -> 1625184 | E64: ='08_Cost_Model'!E9*(1+$B$8)*(1+$D$8) -> 2047731.8 | F64: ='08_Cost_Model'!F9*(1+$B$8)*(1+$D$8) -> 2508471.5 | G64: ='08_Cost_Model'!G9*(1+$B$8)*(1+$D$8) -> 2859657.5 | H64: ='08_Cost_Model'!H9*(1+$B$8)*(1+$D$8) -> 3160674.1
A65: Fixed operating cost | C65: 0 | D65: ='08_Cost_Model'!D21*(1+$E$8) -> 2339451 | E65: ='08_Cost_Model'!E21*(1+$E$8) -> 2481355.4 | F65: ='08_Cost_Model'!F21*(1+$E$8) -> 2631712.9 | G65: ='08_Cost_Model'!G21*(1+$E$8) -> 2784939.8 | H65: ='08_Cost_Model'!H21*(1+$E$8) -> 2943842.8
A66: EBITDA | C66: 0 | D66: =D63-D64-D65 -> 1262565 | E66: =E63-E64-E65 -> 2057184.8 | F66: =F63-F64-F65 -> 2927998.8 | G66: =G63-G64-G65 -> 3553131.5 | H66: =H63-H64-H65 -> 4061394
A67: Depreciation | C67: 0 | D67: ='09_Assets_Depreciation'!D20 -> 333550 | E67: ='09_Assets_Depreciation'!E20 -> 333550 | F67: ='09_Assets_Depreciation'!F20 -> 333550 | G67: ='09_Assets_Depreciation'!G20 -> 333550 | H67: ='09_Assets_Depreciation'!H20 -> 313550
A68: EBIT | C68: 0 | D68: =D66-D67 -> 929015 | E68: =E66-E67 -> 1723634.8 | F68: =F66-F67 -> 2594448.8 | G68: =G66-G67 -> 3219581.5 | H68: =H66-H67 -> 3747844
A69: Tax on EBIT | C69: 0 | D69: =MAX(0,D68)*'04_Assumptions'!$C$40 -> 233833.08 | E69: =MAX(0,E68)*'04_Assumptions'!$C$40 -> 433838.88 | F69: =MAX(0,F68)*'04_Assumptions'!$C$40 -> 653022.75 | G69: =MAX(0,G68)*'04_Assumptions'!$C$40 -> 810368.66 | H69: =MAX(0,H68)*'04_Assumptions'!$C$40 -> 943332.33
A70: NOPAT | C70: 0 | D70: =D68-D69 -> 695181.92 | E70: =E68-E69 -> 1289795.9 | F70: =F68-F69 -> 1941426 | G70: =G68-G69 -> 2409212.8 | H70: =H68-H69 -> 2804511.6
A71: Net working capital | C71: 0 | D71: =D63*'04_Assumptions'!$C$42/365+D64*'04_Assumptions'!$C$43/365-D64*'04_Assumptions'!$C$44/365 -> 15284.515 | E71: =E63*'04_Assumptions'!$C$42/365+E64*'04_Assumptions'!$C$43/365-E64*'04_Assumptions'!$C$44/365 -> 19258.489 | F71: =F63*'04_Assumptions'!$C$42/365+F64*'04_Assumptions'!$C$43/365-F64*'04_Assumptions'!$C$44/365 -> 23591.649 | G71: =G63*'04_Assumptions'!$C$42/365+G64*'04_Assumptions'!$C$43/365-G64*'04_Assumptions'!$C$44/365 -> 26894.48 | H71: =H63*'04_Assumptions'!$C$42/365+H64*'04_Assumptions'!$C$43/365-H64*'04_Assumptions'!$C$44/365 -> 29725.478
A72: Change in NWC | C72: 0 | D72: =D71-C71 -> 15284.515 | E72: =E71-D71 -> 3973.9739 | F72: =F71-E71 -> 4333.16 | G72: =G71-F71 -> 3302.8309 | H72: =H71-G71 -> 2830.9979
A73: Terminal items (Y5) | C73: 0 | D73: 0 | E73: 0 | F73: 0 | G73: 0 | H73: ='15_Project_FCF'!H14+'15_Project_FCF'!H15+'15_Project_FCF'!H16 -> 958342.5
A74: Project FCF | C74: ='15_Project_FCF'!C17 -> -2929530 | D74: =D70+D67-D72+D73 -> 1013447.4 | E74: =E70+E67-E72+E73 -> 1619372 | F74: =F70+F67-F72+F73 -> 2270642.9 | G74: =G70+G67-G72+G73 -> 2739460 | H74: =H70+H67-H72+H73 -> 4073573.1
A75: Cumulative FCF | C75: =C74 -> -2929530 | D75: =C75+D74 -> -1916082.6 | E75: =D75+E74 -> -296710.64 | F75: =E75+F74 -> 1973932.2 | G75: =F75+G74 -> 4713392.2 | H75: =G75+H74 -> 8786965.4
A76: Payback helper | D76: =IF(AND(C75<0,D75>=0),0+(-C75)/D74,0) -> 0 | E76: =IF(AND(D75<0,E75>=0),1+(-D75)/E74,0) -> 0 | F76: =IF(AND(E75<0,F75>=0),2+(-E75)/F74,0) -> 2.1306725 | G76: =IF(AND(F75<0,G75>=0),3+(-F75)/G74,0) -> 0 | H76: =IF(AND(G75<0,H75>=0),4+(-G75)/H74,0) -> 0
A77: NPV | C77: =C74+NPV('04_Assumptions'!$C$74,D74:H74) -> 4633870.4
A78: IRR | C78: =IFERROR(IRR(C74:H74),"n/a") -> 0.53820595
A79: Payback (years) | C79: =IF(SUM(D76:H76)=0,"> 5 yrs",SUM(D76:H76)) -> 2.1306725

Sheet 19_Sensitivity
A1: 19 · Sensitivity Analysis
A2: One variable changed at a time (others at base). Each cell re-runs the full economics from the engine blocks below.
A5: NPV (₹) | B5: Variable
A6: Change in variable → | C6: -0.2 | D6: -0.1 | E6: 0 | F6: 0.1 | G6: 0.2
A7: Selling price | C7: =C47 -> -3203472.7 | D7: =C67 -> -1423256.5 | E7: =C87 -> 203004.1 | F7: =C107 -> 1750188.2 | G7: =C127 -> 3239223.7
A8: Sales volume | C8: =C147 -> -1893398.3 | D8: =C167 -> -820895.67 | E8: =C187 -> 203004.1 | F8: =C207 -> 1212883.7 | G8: =C227 -> 2168298.2
A9: Variable cost | C9: =C247 -> 1332078.2 | D9: =C267 -> 770139.45 | E9: =C287 -> 203004.1 | F9: =C307 -> -364131.25 | G9: =C327 -> -953114.69
A10: Fixed cost | C10: =C347 -> 1690960.6 | D10: =C367 -> 972619.22 | E10: =C387 -> 203004.1 | F10: =C407 -> -569229.86 | G10: =C427 -> -1390066.7
A11: Discount rate | C11: ='16_Appraisal'!C8+NPV('04_Assumptions'!$C$74*(1+C$6),'16_Appraisal'!D8:H8) -> 507907.84 | D11: ='16_Appraisal'!C8+NPV('04_Assumptions'!$C$74*(1+D$6),'16_Appraisal'!D8:H8) -> 350719.39 | E11: ='16_Appraisal'!C8+NPV('04_Assumptions'!$C$74*(1+E$6),'16_Appraisal'!D8:H8) -> 203004.1 | F11: ='16_Appraisal'!C8+NPV('04_Assumptions'!$C$74*(1+F$6),'16_Appraisal'!D8:H8) -> 64071.797 | G11: ='16_Appraisal'!C8+NPV('04_Assumptions'!$C$74*(1+G$6),'16_Appraisal'!D8:H8) -> -66709.393
A13: IRR | C13: =C6 -> -0.2 | D13: =D6 -> -0.1 | E13: =E6 -> 0 | F13: =F6 -> 0.1 | G13: =G6 -> 0.2
A14: Selling price | C14: =C48 -> n/a | D14: =C68 -> -0.012352208 | E14: =C88 -> 0.15261855 | F14: =C108 -> 0.29589475 | G14: =C128 -> 0.42316448
A15: Sales volume | C15: =C148 -> -0.063671148 | D15: =C168 -> 0.050736127 | E15: =C188 -> 0.15261855 | F15: =C208 -> 0.24769449 | G15: =C228 -> 0.33249298
A16: Variable cost | C16: =C248 -> 0.25851905 | D16: =C268 -> 0.20655417 | E16: =C288 -> 0.15261855 | F16: =C308 -> 0.096966879 | G16: =C328 -> 0.037101415
A17: Fixed cost | C17: =C348 -> 0.29441135 | D17: =C368 -> 0.22681037 | E17: =C388 -> 0.15261855 | F17: =C408 -> 0.077265524 | G17: =C428 -> -0.0038859552
A18: Discount rate (IRR unaffected) | C18: ='16_Appraisal'!C17 -> 0.15261855 | D18: ='16_Appraisal'!C17 -> 0.15261855 | E18: ='16_Appraisal'!C17 -> 0.15261855 | F18: ='16_Appraisal'!C17 -> 0.15261855 | G18: ='16_Appraisal'!C17 -> 0.15261855
A20: Ranking of impact on NPV | B20: Lowest NPV | C20: Highest NPV | D20: Swing (₹) | E20: Rank
A21: Selling price | B21: =MIN(C7:G7) -> -3203472.7 | C21: =MAX(C7:G7) -> 3239223.7 | D21: =C21-B21 -> 6442696.4 | E21: =RANK(D21,$D$21:$D$25) -> 1
A22: Sales volume | B22: =MIN(C8:G8) -> -1893398.3 | C22: =MAX(C8:G8) -> 2168298.2 | D22: =C22-B22 -> 4061696.5 | E22: =RANK(D22,$D$21:$D$25) -> 2
A23: Variable cost | B23: =MIN(C9:G9) -> -953114.69 | C23: =MAX(C9:G9) -> 1332078.2 | D23: =C23-B23 -> 2285192.9 | E23: =RANK(D23,$D$21:$D$25) -> 4
A24: Fixed cost | B24: =MIN(C10:G10) -> -1390066.7 | C24: =MAX(C10:G10) -> 1690960.6 | D24: =C24-B24 -> 3081027.2 | E24: =RANK(D24,$D$21:$D$25) -> 3
A25: Discount rate | B25: =MIN(C11:G11) -> -66709.393 | C25: =MAX(C11:G11) -> 507907.84 | D25: =C25-B25 -> 574617.23 | E25: =RANK(D25,$D$21:$D$25) -> 5
A27: Most sensitive variable | B27: =INDEX(A21:A25,MATCH(MAX(D21:D25),D21:D25,0)) -> Selling price
A28: Check: base column NPV − model NPV (must be 0) | E28: =ROUND(E7-'16_Appraisal'!C15,2) -> 0
A29: ±20% range used for all variables (as per assignment template); discount rate flexes as a % of the WACC (e.g. +10% of 13% = 14.3%).
A32: Sensitivity engine: Selling price at level 1 | C32: Year 0 | D32: Year 1 | E32: Year 2 | F32: Year 3 | G32: Year 4 | H32: Year 5
A33: Revenue | C33: 0 | D33: ='07_Revenue_Model'!D11*(1+0)*(1+$C$6) -> 3168000 | E33: ='07_Revenue_Model'!E11*(1+0)*(1+$C$6) -> 3991680 | F33: ='07_Revenue_Model'!F11*(1+0)*(1+$C$6) -> 4889808 | G33: ='07_Revenue_Model'!G11*(1+0)*(1+$C$6) -> 5574381.1 | H33: ='07_Revenue_Model'!H11*(1+0)*(1+$C$6) -> 6161158.1
A34: Variable cost | C34: 0 | D34: ='08_Cost_Model'!D9*(1+0)*(1+0) -> 1425600 | E34: ='08_Cost_Model'!E9*(1+0)*(1+0) -> 1796256 | F34: ='08_Cost_Model'!F9*(1+0)*(1+0) -> 2200413.6 | G34: ='08_Cost_Model'!G9*(1+0)*(1+0) -> 2508471.5 | H34: ='08_Cost_Model'!H9*(1+0)*(1+0) -> 2772521.1
A35: Fixed operating cost | C35: 0 | D35: ='08_Cost_Model'!D21*(1+0) -> 2462580 | E35: ='08_Cost_Model'!E21*(1+0) -> 2611953 | F35: ='08_Cost_Model'!F21*(1+0) -> 2770224.1 | G35: ='08_Cost_Model'!G21*(1+0) -> 2931515.6 | H35: ='08_Cost_Model'!H21*(1+0) -> 3098781.9
A36: EBITDA | C36: 0 | D36: =D33-D34-D35 -> -720180 | E36: =E33-E34-E35 -> -416529 | F36: =F33-F34-F35 -> -80829.738 | G36: =G33-G34-G35 -> 134393.99 | H36: =H33-H34-H35 -> 289855.08
A37: Depreciation | C37: 0 | D37: ='09_Assets_Depreciation'!D20 -> 333550 | E37: ='09_Assets_Depreciation'!E20 -> 333550 | F37: ='09_Assets_Depreciation'!F20 -> 333550 | G37: ='09_Assets_Depreciation'!G20 -> 333550 | H37: ='09_Assets_Depreciation'!H20 -> 313550
A38: EBIT | C38: 0 | D38: =D36-D37 -> -1053730 | E38: =E36-E37 -> -750079 | F38: =F36-F37 -> -414379.74 | G38: =G36-G37 -> -199156.01 | H38: =H36-H37 -> -23694.919
A39: Tax on EBIT | C39: 0 | D39: =MAX(0,D38)*'04_Assumptions'!$C$40 -> 0 | E39: =MAX(0,E38)*'04_Assumptions'!$C$40 -> 0 | F39: =MAX(0,F38)*'04_Assumptions'!$C$40 -> 0 | G39: =MAX(0,G38)*'04_Assumptions'!$C$40 -> 0 | H39: =MAX(0,H38)*'04_Assumptions'!$C$40 -> 0
A40: NOPAT | C40: 0 | D40: =D38-D39 -> -1053730 | E40: =E38-E39 -> -750079 | F40: =F38-F39 -> -414379.74 | G40: =G38-G39 -> -199156.01 | H40: =H38-H39 -> -23694.919
A41: Net working capital | C41: 0 | D41: =D33*'04_Assumptions'!$C$42/365+D34*'04_Assumptions'!$C$43/365-D34*'04_Assumptions'!$C$44/365 -> 5641.6438 | E41: =E33*'04_Assumptions'!$C$42/365+E34*'04_Assumptions'!$C$43/365-E34*'04_Assumptions'!$C$44/365 -> 7108.4712 | F41: =F33*'04_Assumptions'!$C$42/365+F34*'04_Assumptions'!$C$43/365-F34*'04_Assumptions'!$C$44/365 -> 8707.8773 | G41: =G33*'04_Assumptions'!$C$42/365+G34*'04_Assumptions'!$C$43/365-G34*'04_Assumptions'!$C$44/365 -> 9926.9801 | H41: =H33*'04_Assumptions'!$C$42/365+H34*'04_Assumptions'!$C$43/365-H34*'04_Assumptions'!$C$44/365 -> 10971.925
A42: Change in NWC | C42: 0 | D42: =D41-C41 -> 5641.6438 | E42: =E41-D41 -> 1466.8274 | F42: =F41-E41 -> 1599.406 | G42: =G41-F41 -> 1219.1028 | H42: =H41-G41 -> 1044.9453
A43: Terminal items (Y5) | C43: 0 | D43: 0 | E43: 0 | F43: 0 | G43: 0 | H43: ='15_Project_FCF'!H14+'15_Project_FCF'!H15+'15_Project_FCF'!H16 -> 958342.5
A44: Project FCF | C44: ='15_Project_FCF'!C17 -> -2929530 | D44: =D40+D37-D42+D43 -> -725821.64 | E44: =E40+E37-E42+E43 -> -417995.83 | F44: =F40+F37-F42+F43 -> -82429.144 | G44: =G40+G37-G42+G43 -> 133174.88 | H44: =H40+H37-H42+H43 -> 1247152.6
A45: Cumulative FCF | C45: =C44 -> -2929530 | D45: =C45+D44 -> -3655351.6 | E45: =D45+E44 -> -4073347.5 | F45: =E45+F44 -> -4155776.6 | G45: =F45+G44 -> -4022601.7 | H45: =G45+H44 -> -2775449.1
A46: Payback helper | D46: =IF(AND(C45<0,D45>=0),0+(-C45)/D44,0) -> 0 | E46: =IF(AND(D45<0,E45>=0),1+(-D45)/E44,0) -> 0 | F46: =IF(AND(E45<0,F45>=0),2+(-E45)/F44,0) -> 0 | G46: =IF(AND(F45<0,G45>=0),3+(-F45)/G44,0) -> 0 | H46: =IF(AND(G45<0,H45>=0),4+(-G45)/H44,0) -> 0
A47: NPV | C47: =C44+NPV('04_Assumptions'!$C$74,D44:H44) -> -3203472.7
A48: IRR | C48: =IFERROR(IRR(C44:H44),"n/a") -> n/a
A49: Payback (years) | C49: =IF(SUM(D46:H46)=0,"> 5 yrs",SUM(D46:H46)) -> > 5 yrs
A52: Sensitivity engine: Selling price at level 2 | C52: Year 0 | D52: Year 1 | E52: Year 2 | F52: Year 3 | G52: Year 4 | H52: Year 5
A53: Revenue | C53: 0 | D53: ='07_Revenue_Model'!D11*(1+0)*(1+$D$6) -> 3564000 | E53: ='07_Revenue_Model'!E11*(1+0)*(1+$D$6) -> 4490640 | F53: ='07_Revenue_Model'!F11*(1+0)*(1+$D$6) -> 5501034 | G53: ='07_Revenue_Model'!G11*(1+0)*(1+$D$6) -> 6271178.8 | H53: ='07_Revenue_Model'!H11*(1+0)*(1+$D$6) -> 6931302.8
A54: Variable cost | C54: 0 | D54: ='08_Cost_Model'!D9*(1+0)*(1+0) -> 1425600 | E54: ='08_Cost_Model'!E9*(1+0)*(1+0) -> 1796256 | F54: ='08_Cost_Model'!F9*(1+0)*(1+0) -> 2200413.6 | G54: ='08_Cost_Model'!G9*(1+0)*(1+0) -> 2508471.5 | H54: ='08_Cost_Model'!H9*(1+0)*(1+0) -> 2772521.1
A55: Fixed operating cost | C55: 0 | D55: ='08_Cost_Model'!D21*(1+0) -> 2462580 | E55: ='08_Cost_Model'!E21*(1+0) -> 2611953 | F55: ='08_Cost_Model'!F21*(1+0) -> 2770224.1 | G55: ='08_Cost_Model'!G21*(1+0) -> 2931515.6 | H55: ='08_Cost_Model'!H21*(1+0) -> 3098781.9
A56: EBITDA | C56: 0 | D56: =D53-D54-D55 -> -324180 | E56: =E53-E54-E55 -> 82431 | F56: =F53-F54-F55 -> 530396.26 | G56: =G53-G54-G55 -> 831191.63 | H56: =H53-H54-H55 -> 1059999.8
A57: Depreciation | C57: 0 | D57: ='09_Assets_Depreciation'!D20 -> 333550 | E57: ='09_Assets_Depreciation'!E20 -> 333550 | F57: ='09_Assets_Depreciation'!F20 -> 333550 | G57: ='09_Assets_Depreciation'!G20 -> 333550 | H57: ='09_Assets_Depreciation'!H20 -> 313550
A58: EBIT | C58: 0 | D58: =D56-D57 -> -657730 | E58: =E56-E57 -> -251119 | F58: =F56-F57 -> 196846.26 | G58: =G56-G57 -> 497641.63 | H58: =H56-H57 -> 746449.84
A59: Tax on EBIT | C59: 0 | D59: =MAX(0,D58)*'04_Assumptions'!$C$40 -> 0 | E59: =MAX(0,E58)*'04_Assumptions'!$C$40 -> 0 | F59: =MAX(0,F58)*'04_Assumptions'!$C$40 -> 49546.204 | G59: =MAX(0,G58)*'04_Assumptions'!$C$40 -> 125256.4 | H59: =MAX(0,H58)*'04_Assumptions'!$C$40 -> 187881.43
A60: NOPAT | C60: 0 | D60: =D58-D59 -> -657730 | E60: =E58-E59 -> -251119 | F60: =F58-F59 -> 147300.06 | G60: =G58-G59 -> 372385.23 | H60: =H58-H59 -> 558568.42
A61: Net working capital | C61: 0 | D61: =D53*'04_Assumptions'!$C$42/365+D54*'04_Assumptions'!$C$43/365-D54*'04_Assumptions'!$C$44/365 -> 7811.5068 | E61: =E53*'04_Assumptions'!$C$42/365+E54*'04_Assumptions'!$C$43/365-E54*'04_Assumptions'!$C$44/365 -> 9842.4986 | F61: =F53*'04_Assumptions'!$C$42/365+F54*'04_Assumptions'!$C$43/365-F54*'04_Assumptions'!$C$44/365 -> 12057.061 | G61: =G53*'04_Assumptions'!$C$42/365+G54*'04_Assumptions'!$C$43/365-G54*'04_Assumptions'!$C$44/365 -> 13745.049 | H61: =H53*'04_Assumptions'!$C$42/365+H54*'04_Assumptions'!$C$43/365-H54*'04_Assumptions'!$C$44/365 -> 15191.897
A62: Change in NWC | C62: 0 | D62: =D61-C61 -> 7811.5068 | E62: =E61-D61 -> 2030.9918 | F62: =F61-E61 -> 2214.5622 | G62: =G61-F61 -> 1687.9885 | H62: =H61-G61 -> 1446.8473
A63: Terminal items (Y5) | C63: 0 | D63: 0 | E63: 0 | F63: 0 | G63: 0 | H63: ='15_Project_FCF'!H14+'15_Project_FCF'!H15+'15_Project_FCF'!H16 -> 958342.5
A64: Project FCF | C64: ='15_Project_FCF'!C17 -> -2929530 | D64: =D60+D57-D62+D63 -> -331991.51 | E64: =E60+E57-E62+E63 -> 80400.008 | F64: =F60+F57-F62+F63 -> 478635.5 | G64: =G60+G57-G62+G63 -> 704247.24 | H64: =H60+H57-H62+H63 -> 1829014.1
A65: Cumulative FCF | C65: =C64 -> -2929530 | D65: =C65+D64 -> -3261521.5 | E65: =D65+E64 -> -3181121.5 | F65: =E65+F64 -> -2702486 | G65: =F65+G64 -> -1998238.8 | H65: =G65+H64 -> -169224.69
A66: Payback helper | D66: =IF(AND(C65<0,D65>=0),0+(-C65)/D64,0) -> 0 | E66: =IF(AND(D65<0,E65>=0),1+(-D65)/E64,0) -> 0 | F66: =IF(AND(E65<0,F65>=0),2+(-E65)/F64,0) -> 0 | G66: =IF(AND(F65<0,G65>=0),3+(-F65)/G64,0) -> 0 | H66: =IF(AND(G65<0,H65>=0),4+(-G65)/H64,0) -> 0
A67: NPV | C67: =C64+NPV('04_Assumptions'!$C$74,D64:H64) -> -1423256.5
A68: IRR | C68: =IFERROR(IRR(C64:H64),"n/a") -> -0.012352208
A69: Payback (years) | C69: =IF(SUM(D66:H66)=0,"> 5 yrs",SUM(D66:H66)) -> > 5 yrs
A72: Sensitivity engine: Selling price at level 3 | C72: Year 0 | D72: Year 1 | E72: Year 2 | F72: Year 3 | G72: Year 4 | H72: Year 5
A73: Revenue | C73: 0 | D73: ='07_Revenue_Model'!D11*(1+0)*(1+$E$6) -> 3960000 | E73: ='07_Revenue_Model'!E11*(1+0)*(1+$E$6) -> 4989600 | F73: ='07_Revenue_Model'!F11*(1+0)*(1+$E$6) -> 6112260 | G73: ='07_Revenue_Model'!G11*(1+0)*(1+$E$6) -> 6967976.4 | H73: ='07_Revenue_Model'!H11*(1+0)*(1+$E$6) -> 7701447.6
A74: Variable cost | C74: 0 | D74: ='08_Cost_Model'!D9*(1+0)*(1+0) -> 1425600 | E74: ='08_Cost_Model'!E9*(1+0)*(1+0) -> 1796256 | F74: ='08_Cost_Model'!F9*(1+0)*(1+0) -> 2200413.6 | G74: ='08_Cost_Model'!G9*(1+0)*(1+0) -> 2508471.5 | H74: ='08_Cost_Model'!H9*(1+0)*(1+0) -> 2772521.1
A75: Fixed operating cost | C75: 0 | D75: ='08_Cost_Model'!D21*(1+0) -> 2462580 | E75: ='08_Cost_Model'!E21*(1+0) -> 2611953 | F75: ='08_Cost_Model'!F21*(1+0) -> 2770224.1 | G75: ='08_Cost_Model'!G21*(1+0) -> 2931515.6 | H75: ='08_Cost_Model'!H21*(1+0) -> 3098781.9
A76: EBITDA | C76: 0 | D76: =D73-D74-D75 -> 71820 | E76: =E73-E74-E75 -> 581391 | F76: =F73-F74-F75 -> 1141622.3 | G76: =G73-G74-G75 -> 1527989.3 | H76: =H73-H74-H75 -> 1830144.6
A77: Depreciation | C77: 0 | D77: ='09_Assets_Depreciation'!D20 -> 333550 | E77: ='09_Assets_Depreciation'!E20 -> 333550 | F77: ='09_Assets_Depreciation'!F20 -> 333550 | G77: ='09_Assets_Depreciation'!G20 -> 333550 | H77: ='09_Assets_Depreciation'!H20 -> 313550
A78: EBIT | C78: 0 | D78: =D76-D77 -> -261730 | E78: =E76-E77 -> 247841 | F78: =F76-F77 -> 808072.26 | G78: =G76-G77 -> 1194439.3 | H78: =H76-H77 -> 1516594.6
A79: Tax on EBIT | C79: 0 | D79: =MAX(0,D78)*'04_Assumptions'!$C$40 -> 0 | E79: =MAX(0,E78)*'04_Assumptions'!$C$40 -> 62381.58 | F79: =MAX(0,F78)*'04_Assumptions'!$C$40 -> 203391.79 | G79: =MAX(0,G78)*'04_Assumptions'!$C$40 -> 300640.36 | H79: =MAX(0,H78)*'04_Assumptions'!$C$40 -> 381726.86
A80: NOPAT | C80: 0 | D80: =D78-D79 -> -261730 | E80: =E78-E79 -> 185459.42 | F80: =F78-F79 -> 604680.47 | G80: =G78-G79 -> 893798.9 | H80: =H78-H79 -> 1134867.7
A81: Net working capital | C81: 0 | D81: =D73*'04_Assumptions'!$C$42/365+D74*'04_Assumptions'!$C$43/365-D74*'04_Assumptions'!$C$44/365 -> 9981.3699 | E81: =E73*'04_Assumptions'!$C$42/365+E74*'04_Assumptions'!$C$43/365-E74*'04_Assumptions'!$C$44/365 -> 12576.526 | F81: =F73*'04_Assumptions'!$C$42/365+F74*'04_Assumptions'!$C$43/365-F74*'04_Assumptions'!$C$44/365 -> 15406.244 | G81: =G73*'04_Assumptions'!$C$42/365+G74*'04_Assumptions'!$C$43/365-G74*'04_Assumptions'!$C$44/365 -> 17563.119 | H81: =H73*'04_Assumptions'!$C$42/365+H74*'04_Assumptions'!$C$43/365-H74*'04_Assumptions'!$C$44/365 -> 19411.868
A82: Change in NWC | C82: 0 | D82: =D81-C81 -> 9981.3699 | E82: =E81-D81 -> 2595.1562 | F82: =F81-E81 -> 2829.7184 | G82: =G81-F81 -> 2156.8742 | H82: =H81-G81 -> 1848.7493
A83: Terminal items (Y5) | C83: 0 | D83: 0 | E83: 0 | F83: 0 | G83: 0 | H83: ='15_Project_FCF'!H14+'15_Project_FCF'!H15+'15_Project_FCF'!H16 -> 958342.5
A84: Project FCF | C84: ='15_Project_FCF'!C17 -> -2929530 | D84: =D80+D77-D82+D83 -> 61838.63 | E84: =E80+E77-E82+E83 -> 516414.26 | F84: =F80+F77-F82+F83 -> 935400.76 | G84: =G80+G77-G82+G83 -> 1225192 | H84: =H80+H77-H82+H83 -> 2404911.5
A85: Cumulative FCF | C85: =C84 -> -2929530 | D85: =C85+D84 -> -2867691.4 | E85: =D85+E84 -> -2351277.1 | F85: =E85+F84 -> -1415876.4 | G85: =F85+G84 -> -190684.32 | H85: =G85+H84 -> 2214227.2
A86: Payback helper | D86: =IF(AND(C85<0,D85>=0),0+(-C85)/D84,0) -> 0 | E86: =IF(AND(D85<0,E85>=0),1+(-D85)/E84,0) -> 0 | F86: =IF(AND(E85<0,F85>=0),2+(-E85)/F84,0) -> 0 | G86: =IF(AND(F85<0,G85>=0),3+(-F85)/G84,0) -> 0 | H86: =IF(AND(G85<0,H85>=0),4+(-G85)/H84,0) -> 4.0792895
A87: NPV | C87: =C84+NPV('04_Assumptions'!$C$74,D84:H84) -> 203004.1
A88: IRR | C88: =IFERROR(IRR(C84:H84),"n/a") -> 0.15261855
A89: Payback (years) | C89: =IF(SUM(D86:H86)=0,"> 5 yrs",SUM(D86:H86)) -> 4.0792895
A92: Sensitivity engine: Selling price at level 4 | C92: Year 0 | D92: Year 1 | E92: Year 2 | F92: Year 3 | G92: Year 4 | H92: Year 5
A93: Revenue | C93: 0 | D93: ='07_Revenue_Model'!D11*(1+0)*(1+$F$6) -> 4356000 | E93: ='07_Revenue_Model'!E11*(1+0)*(1+$F$6) -> 5488560 | F93: ='07_Revenue_Model'!F11*(1+0)*(1+$F$6) -> 6723486 | G93: ='07_Revenue_Model'!G11*(1+0)*(1+$F$6) -> 7664774 | H93: ='07_Revenue_Model'!H11*(1+0)*(1+$F$6) -> 8471592.4
A94: Variable cost | C94: 0 | D94: ='08_Cost_Model'!D9*(1+0)*(1+0) -> 1425600 | E94: ='08_Cost_Model'!E9*(1+0)*(1+0) -> 1796256 | F94: ='08_Cost_Model'!F9*(1+0)*(1+0) -> 2200413.6 | G94: ='08_Cost_Model'!G9*(1+0)*(1+0) -> 2508471.5 | H94: ='08_Cost_Model'!H9*(1+0)*(1+0) -> 2772521.1
A95: Fixed operating cost | C95: 0 | D95: ='08_Cost_Model'!D21*(1+0) -> 2462580 | E95: ='08_Cost_Model'!E21*(1+0) -> 2611953 | F95: ='08_Cost_Model'!F21*(1+0) -> 2770224.1 | G95: ='08_Cost_Model'!G21*(1+0) -> 2931515.6 | H95: ='08_Cost_Model'!H21*(1+0) -> 3098781.9
A96: EBITDA | C96: 0 | D96: =D93-D94-D95 -> 467820 | E96: =E93-E94-E95 -> 1080351 | F96: =F93-F94-F95 -> 1752848.3 | G96: =G93-G94-G95 -> 2224786.9 | H96: =H93-H94-H95 -> 2600289.4
A97: Depreciation | C97: 0 | D97: ='09_Assets_Depreciation'!D20 -> 333550 | E97: ='09_Assets_Depreciation'!E20 -> 333550 | F97: ='09_Assets_Depreciation'!F20 -> 333550 | G97: ='09_Assets_Depreciation'!G20 -> 333550 | H97: ='09_Assets_Depreciation'!H20 -> 313550
A98: EBIT | C98: 0 | D98: =D96-D97 -> 134270 | E98: =E96-E97 -> 746801 | F98: =F96-F97 -> 1419298.3 | G98: =G96-G97 -> 1891236.9 | H98: =H96-H97 -> 2286739.4
A99: Tax on EBIT | C99: 0 | D99: =MAX(0,D98)*'04_Assumptions'!$C$40 -> 33795.759 | E99: =MAX(0,E98)*'04_Assumptions'!$C$40 -> 187969.81 | F99: =MAX(0,F98)*'04_Assumptions'!$C$40 -> 357237.37 | G99: =MAX(0,G98)*'04_Assumptions'!$C$40 -> 476024.33 | H99: =MAX(0,H98)*'04_Assumptions'!$C$40 -> 575572.3
A100: NOPAT | C100: 0 | D100: =D98-D99 -> 100474.24 | E100: =E98-E99 -> 558831.19 | F100: =F98-F99 -> 1062060.9 | G100: =G98-G99 -> 1415212.6 | H100: =H98-H99 -> 1711167.1
A101: Net working capital | C101: 0 | D101: =D93*'04_Assumptions'!$C$42/365+D94*'04_Assumptions'!$C$43/365-D94*'04_Assumptions'!$C$44/365 -> 12151.233 | E101: =E93*'04_Assumptions'!$C$42/365+E94*'04_Assumptions'!$C$43/365-E94*'04_Assumptions'!$C$44/365 -> 15310.553 | F101: =F93*'04_Assumptions'!$C$42/365+F94*'04_Assumptions'!$C$43/365-F94*'04_Assumptions'!$C$44/365 -> 18755.428 | G101: =G93*'04_Assumptions'!$C$42/365+G94*'04_Assumptions'!$C$43/365-G94*'04_Assumptions'!$C$44/365 -> 21381.188 | H101: =H93*'04_Assumptions'!$C$42/365+H94*'04_Assumptions'!$C$43/365-H94*'04_Assumptions'!$C$44/365 -> 23631.839
A102: Change in NWC | C102: 0 | D102: =D101-C101 -> 12151.233 | E102: =E101-D101 -> 3159.3205 | F102: =F101-E101 -> 3444.8745 | G102: =G101-F101 -> 2625.7599 | H102: =H101-G101 -> 2250.6514
A103: Terminal items (Y5) | C103: 0 | D103: 0 | E103: 0 | F103: 0 | G103: 0 | H103: ='15_Project_FCF'!H14+'15_Project_FCF'!H15+'15_Project_FCF'!H16 -> 958342.5
A104: Project FCF | C104: ='15_Project_FCF'!C17 -> -2929530 | D104: =D100+D97-D102+D103 -> 421873.01 | E104: =E100+E97-E102+E103 -> 889221.87 | F104: =F100+F97-F102+F103 -> 1392166 | G104: =G100+G97-G102+G103 -> 1746136.8 | H104: =H100+H97-H102+H103 -> 2980808.9
A105: Cumulative FCF | C105: =C104 -> -2929530 | D105: =C105+D104 -> -2507657 | E105: =D105+E104 -> -1618435.1 | F105: =E105+F104 -> -226269.11 | G105: =F105+G104 -> 1519867.7 | H105: =G105+H104 -> 4500676.6
A106: Payback helper | D106: =IF(AND(C105<0,D105>=0),0+(-C105)/D104,0) -> 0 | E106: =IF(AND(D105<0,E105>=0),1+(-D105)/E104,0) -> 0 | F106: =IF(AND(E105<0,F105>=0),2+(-E105)/F104,0) -> 0 | G106: =IF(AND(F105<0,G105>=0),3+(-F105)/G104,0) -> 3.1295827 | H106: =IF(AND(G105<0,H105>=0),4+(-G105)/H104,0) -> 0
A107: NPV | C107: =C104+NPV('04_Assumptions'!$C$74,D104:H104) -> 1750188.2
A108: IRR | C108: =IFERROR(IRR(C104:H104),"n/a") -> 0.29589475
A109: Payback (years) | C109: =IF(SUM(D106:H106)=0,"> 5 yrs",SUM(D106:H106)) -> 3.1295827
A112: Sensitivity engine: Selling price at level 5 | C112: Year 0 | D112: Year 1 | E112: Year 2 | F112: Year 3 | G112: Year 4 | H112: Year 5
A113: Revenue | C113: 0 | D113: ='07_Revenue_Model'!D11*(1+0)*(1+$G$6) -> 4752000 | E113: ='07_Revenue_Model'!E11*(1+0)*(1+$G$6) -> 5987520 | F113: ='07_Revenue_Model'!F11*(1+0)*(1+$G$6) -> 7334712 | G113: ='07_Revenue_Model'!G11*(1+0)*(1+$G$6) -> 8361571.7 | H113: ='07_Revenue_Model'!H11*(1+0)*(1+$G$6) -> 9241737.1
A114: Variable cost | C114: 0 | D114: ='08_Cost_Model'!D9*(1+0)*(1+0) -> 1425600 | E114: ='08_Cost_Model'!E9*(1+0)*(1+0) -> 1796256 | F114: ='08_Cost_Model'!F9*(1+0)*(1+0) -> 2200413.6 | G114: ='08_Cost_Model'!G9*(1+0)*(1+0) -> 2508471.5 | H114: ='08_Cost_Model'!H9*(1+0)*(1+0) -> 2772521.1
A115: Fixed operating cost | C115: 0 | D115: ='08_Cost_Model'!D21*(1+0) -> 2462580 | E115: ='08_Cost_Model'!E21*(1+0) -> 2611953 | F115: ='08_Cost_Model'!F21*(1+0) -> 2770224.1 | G115: ='08_Cost_Model'!G21*(1+0) -> 2931515.6 | H115: ='08_Cost_Model'!H21*(1+0) -> 3098781.9
...

Sheet 20_Dashboard
A1: 20 · Investment Committee Dashboard
A2: One-page decision summary. Every number is a live link; change an assumption and this page updates.
A4: Metric | B4: Value | C4: What it means
A5: Project | B5: Campus Brew Café, near LPU (Phagwara) | C5: Small 30-seat café serving students and staff
A6: Initial investment (Year 0) | B6: ='06_Investment_Funding'!B15 -> 2929530 | C6: Cash committed before opening
A7: Year-1 revenue | B7: ='12_Income_Statement'!D6 -> 3960000 | C7: Starting operating scale
A8: Year-5 revenue | B8: ='12_Income_Statement'!H6 -> 7701447.6 | C8: Scale after five years
A9: Year-5 EBITDA | B9: ='12_Income_Statement'!H10 -> 1830144.6 | C9: Operating profitability
A10: Year-5 net profit | B10: ='12_Income_Statement'!H16 -> 1112946.1 | C10: Bottom-line profitability
A11: Required return (WACC) | B11: ='16_Appraisal'!C6 -> 0.132915 | C11: Minimum return the project must earn
A12: NPV | B12: ='16_Appraisal'!C15 -> 203004.1 | C12: Value created (positive) or destroyed (negative)
A13: Project IRR | B13: ='16_Appraisal'!C17 -> 0.15261855 | C13: Yearly return earned on the project
A14: Payback (years) | B14: ='16_Appraisal'!C19 -> 4.0792895 | C14: Time to recover the initial investment
A15: Break-even customers per day (Year 1) | B15: ='17_Break_Even'!B11 -> 72.874645 | C15: Minimum daily customers to cover fixed costs
A16: Break-even revenue (Year 1, ₹) | B16: ='17_Break_Even'!B12 -> 3847781.2 | C16: Sales needed to cover fixed costs
A17: Base-case decision | B17: ='16_Appraisal'!C22 -> Invest with Conditions | C17: Follows the numbers: NPV, IRR, payback and downside
A18: Key risk (most sensitive variable) | B18: ='19_Sensitivity'!B27 -> Selling price | C18: Variable whose ±20% swing moves NPV the most
A19: Downside result: pessimistic NPV | B19: ='18_Scenarios'!E12 -> -4892237.1 | C19: Volume −20%, price −10%, variable cost +10%, fixed cost +10%
A20: Downside result: pessimistic IRR | B20: ='18_Scenarios'!F12 -> n/a | C20: Return in the pessimistic case
A21: Optimistic NPV | B21: ='18_Scenarios'!E14 -> 4633870.4 | C21: Volume +20%, price +10%, variable cost −5%, fixed cost −5%
A24: Chart data (linked) | D24: Year 1 | E24: Year 2 | F24: Year 3 | G24: Year 4 | H24: Year 5
A25: Revenue | C25: Revenue | D25: ='12_Income_Statement'!D6 -> 3960000 | E25: ='12_Income_Statement'!E6 -> 4989600 | F25: ='12_Income_Statement'!F6 -> 6112260 | G25: ='12_Income_Statement'!G6 -> 6967976.4 | H25: ='12_Income_Statement'!H6 -> 7701447.6
A26: EBITDA | C26: EBITDA | D26: ='12_Income_Statement'!D10 -> 71820 | E26: ='12_Income_Statement'!E10 -> 581391 | F26: ='12_Income_Statement'!F10 -> 1141622.3 | G26: ='12_Income_Statement'!G10 -> 1527989.3 | H26: ='12_Income_Statement'!H10 -> 1830144.6
A27: Net profit | C27: Net profit | D27: ='12_Income_Statement'!D16 -> -408206.5 | E27: ='12_Income_Statement'!E16 -> 97772.728 | F27: ='12_Income_Statement'!F16 -> 538915.45 | G27: ='12_Income_Statement'!G16 -> 849955.56 | H27: ='12_Income_Statement'!H16 -> 1112946.1
A28: Project FCF | C28: Project FCF | D28: ='15_Project_FCF'!D17 -> 61838.63 | E28: ='15_Project_FCF'!E17 -> 516414.26 | F28: ='15_Project_FCF'!F17 -> 935400.76 | G28: ='15_Project_FCF'!G17 -> 1225192 | H28: ='15_Project_FCF'!H17 -> 2404911.5

Sheet 21_Report_Pitch
A1: 21 · Report & LinkedIn Pitch Outline
A2: The written report follows this exact sequence. Key numbers below are live links to the model.
A4: Report section | B4: What to write | C4: Key number (linked) | D4: Where in workbook
A5: 1. Executive Summary | B5: Project, investment, Year-1/Year-5 performance, NPV, IRR, payback, key risk, recommendation. | C5: ="NPV ₹"&TEXT('16_Appraisal'!C15,"#,##0")&" | IRR "&TEXT('16_Appraisal'!C17,"0.0%") -> NPV ₹203,004 | IRR 15.3% | D5: 16, 20
A6: 2. Business Opportunity | B6: Problem, solution, customer, geography, business model. | C6: Sheet 01 text | D6: 01
A7: 3. Market & Evidence | B7: Research method, sources, verification, limitations (see honest status column). | C7: Sources 15; see status | D7: 02, 03
A8: 4. Operating Model | B8: Seats, turns, days, average bill, unit of economics. | C8: =TEXT('05_Operating_Drivers'!D11,"#,##0")&" customers in Year 1" -> 24,750 customers in Year 1 | D8: 05, 07
A9: 5. Investment & Funding | B9: Capex, deposit, opening cash, debt and equity. | C9: ="Investment ₹"&TEXT('06_Investment_Funding'!B15,"#,##0") -> Investment ₹2,929,530 | D9: 06, 09, 10
A10: 6. Assumptions | B10: Most important assumptions, sources, rationale. | C10: Seat turns, avg bill, rent, food cost | D10: 04
A11: 7. Financial Forecast | B11: Income statement, cash flow, balance sheet with comments. | C11: ="Year-5 revenue ₹"&TEXT('12_Income_Statement'!H6,"#,##0") -> Year-5 revenue ₹7,701,448 | D11: 12, 13, 14
A12: 8. Project FCF & Appraisal | B12: FCF, NPV, IRR, payback and what they mean. | C12: ="Payback "&TEXT('16_Appraisal'!C19,"0.0")&" years" -> Payback 4.1 years | D12: 15, 16
A13: 9. Break-even | B13: Contribution, break-even customers per day, margin of safety. | C13: =TEXT('17_Break_Even'!B11,"#,##0")&" customers/day to break even (Year 1)" -> 73 customers/day to break even (Year 1) | D13: 17
A14: 10. Scenario & Sensitivity | B14: Pessimistic/base/optimistic and the variable that matters most. | C14: ="Most sensitive: "&'19_Sensitivity'!B27 -> Most sensitive: Selling price | D14: 18, 19
A15: 11. Investment Recommendation | B15: Decision with conditions and monitoring triggers. | C15: ='16_Appraisal'!C22 -> Invest with Conditions | D15: 16, 20
A16: 12. Risks & Limitations | B16: Commercial, operational, financial, data and model limitations (many inputs are estimates). | C16: See 02 status column | D16: 02, 22
A17: 13. References | B17: List SRC-01 to SRC-15. | C17: Sheet 02 | D17: 02
A18: 14. Appendix | B18: Supporting calculations. | C18: Sheets 05-15 | D18: All
A21: LinkedIn video (2-3 minutes) - hashtags: #LovelyProfessionalUniversity #MSOB #QDO6FINANCE #DrBasit
A22: 0:00-0:30 | B22: Business problem, customer and solution
A23: 0:30-1:00 | B23: Initial investment and funding
A24: 1:00-1:30 | B24: Operating drivers, revenue and cost model
A25: 1:30-2:00 | B25: Financial performance, NPV, IRR, payback
A26: 2:00-2:20 | B26: Scenarios, sensitivity and biggest risk
A27: 2:20-2:40 | B27: Final investment recommendation

Sheet 22_QA_Viva
A1: 22 · QA Checks & Viva Preparation
A2: Automatic checks (PASS/FAIL). All must show PASS before submission.
A4: Check | B4: Result | C4: What it tests
A5: Funding equals investment | B5: =IF(ABS('06_Investment_Funding'!B22)<1,"PASS","FAIL") -> PASS | C5: Debt + equity = total Year-0 investment
A6: Balance sheet balances in every year | B6: =IF(SUMPRODUCT(ABS('14_Balance_Sheet'!C22:H22))<1,"PASS","FAIL") -> PASS | C6: Total assets = liabilities + equity, Year 0 to 5
A7: Debt fully repaid by end of tenor | B7: =IF(ABS('10_Debt_Schedule'!H9)<1,"PASS","FAIL") -> PASS | C7: Opening + new − repayment = closing; closes at zero
A8: Depreciation in income statement equals asset schedule | B8: =IF(ABS(SUM('12_Income_Statement'!D11:H11)-SUM('09_Assets_Depreciation'!D20:H20))<1,"PASS","FAIL") -> PASS | C8: Depreciation linked, not retyped
A9: Closing cash equals balance-sheet cash | B9: =IF(ABS('13_Cash_Flow'!H21-'14_Balance_Sheet'!H10)<1,"PASS","FAIL") -> PASS | C9: Cash flow statement reconciles to balance sheet
A10: Project FCF uses EBIT (excludes interest & loan flows) | B10: =IF(ABS(SUM('15_Project_FCF'!D6:H6)-SUM('12_Income_Statement'!D12:H12))<1,"PASS","FAIL") -> PASS | C10: FCF starts from EBIT, not net profit
A11: NPV and IRR use the same FCF series | B11: =IF(ABS(SUM('16_Appraisal'!C8:H8)-SUM('15_Project_FCF'!C17:H17))<1,"PASS","FAIL") -> PASS | C11: Appraisal row equals Project FCF row
A12: NPV formula agrees with sum of present values | B12: =IF(ABS('16_Appraisal'!C15-'16_Appraisal'!C16)<1,"PASS","FAIL") -> PASS | C12: Two independent NPV calculations match
A13: Scenario base case equals model NPV | B13: =IF(ABS('18_Scenarios'!E16)<1,"PASS","FAIL") -> PASS | C13: Scenarios flow through the same economics
A14: Sensitivity base column equals model NPV | B14: =IF(ABS('19_Sensitivity'!E28)<1,"PASS","FAIL") -> PASS | C14: Sensitivity engine agrees with the model
A15: Dashboard NPV equals appraisal NPV | B15: =IF(ABS('20_Dashboard'!B12-'16_Appraisal'!C15)<1,"PASS","FAIL") -> PASS | C15: Dashboard is linked
A16: Contribution per customer is positive | B16: =IF('17_Break_Even'!B7>0,"PASS","FAIL") -> PASS | C16: Break-even logic is valid
A17: OVERALL | B17: =IF(COUNTIF(B5:B16,"PASS")=12,"ALL PASS","REVIEW") -> ALL PASS
A20: VIVA PREPARATION - plain-language answers (numbers update automatically) | C20: Answer
A21: Why did you choose this project? | C21: A café is easy to understand and near a large university. It lets us test a real investment decision with clear drivers: seats, turns and bills.
A22: What is the unit of economics? | C22: One paid customer visit. Revenue = seats × seat turns per day × days open × average bill.
A23: How did you forecast Year-1 volume? | C23: ="Start with capacity: "&'04_Assumptions'!$C$6&" seats × "&TEXT('05_Operating_Drivers'!D7,"0.0")&" turns/day × "&'04_Assumptions'!$C$7&" days = "&TEXT('05_Operating_Drivers'!D11,"#,##0")&" customers. Turns ramp up in later years as the café becomes known." -> Start with capacity: 30 seats × 2.5 turns/day × 330 days = 24,750 customers. Turns ramp up in later years as the café becomes known.
A24: Where did the selling price come from? | C24: Average bill is an estimate based on campus-café pricing (beverage plus snack). It grows with inflation. We tested ±20% in the sensitivity analysis.
A25: Which costs are variable? | C25: Ingredients and packaging (36% of sales). Salaries and rent are fixed; electricity is semi-variable (60% fixed).
A26: Why is Project FCF different from accounting profit? | C26: FCF adds back non-cash depreciation, subtracts capex and working-capital build-up, and ignores financing. Profit ignores capex and cash timing.
A27: Why is interest excluded from Project FCF? | C27: The project is judged on its own economics. Financing is captured in the discount rate (WACC); including interest as well would double count the cost of capital.
A28: Why did you choose this discount rate? | C28: ="WACC of "&TEXT('16_Appraisal'!C6,"0.0%")&": cost of equity (risk-free 7.1% + market premium + start-up premium) blended with after-tax cost of debt at a 50:50 funding mix." -> WACC of 13.3%: cost of equity (risk-free 7.1% + market premium + start-up premium) blended with after-tax cost of debt at a 50:50 funding mix.
A29: Explain the NPV formula. | C29: NPV = Year-0 cash flow + PV of Years 1-5 cash flows discounted at the required return. In Excel: =C8+NPV(rate, D8:H8) on 16_Appraisal.
A30: Explain the IRR. | C30: IRR is the yearly return that makes NPV zero. If IRR is above the required return the project earns more than the cost of capital.
A31: How did you calculate payback? | C31: Cumulative FCF is tracked until it turns positive; the fraction of that year = unrecovered balance ÷ that year's cash flow.
A32: What is your break-even? | C32: =TEXT('17_Break_Even'!B11,"#,##0")&" customers per day in Year 1 (fixed costs ÷ contribution per customer). Projected Year-1 volume is "&TEXT('05_Operating_Drivers'!D12,"#,##0")&" per day." -> 73 customers per day in Year 1 (fixed costs ÷ contribution per customer). Projected Year-1 volume is 75 per day.
A33: What happens if sales fall 20%? | C33: ="See 19_Sensitivity. NPV at −20% volume is ₹"&TEXT('19_Sensitivity'!C8,"#,##0")&" versus ₹"&TEXT('16_Appraisal'!C15,"#,##0")&" base." -> See 19_Sensitivity. NPV at −20% volume is ₹-1,893,398 versus ₹203,004 base.
A34: Which scenario does the greatest damage? | C34: ='18_Scenarios'!B17 -> Pessimistic scenario: NPV falls by ₹5,095,241 versus base
A35: Which assumption has the greatest impact on NPV? | C35: ="According to the sensitivity ranking: "&'19_Sensitivity'!B27&"." -> According to the sensitivity ranking: Selling price.
A36: What would make you reject the project? | C36: If the pessimistic case stays deeply negative and footfall evidence (competitor visits, menu prices, quotes) does not support turns of about 3 or more per day.
A37: Show a random formula and change an assumption live. | C37: Example: change seat turns in 04_Assumptions. Revenue (07), costs (08), statements (12-14), FCF (15), NPV (16) and the dashboard all update; balance check stays zero.
